playground/src/d-flipflop/DFF_N/DFF_N.vhd
--------------------------------------------------------------------------------
-- generic  D-FlipFlop
--------------------------------------------------------------------------------

library IEEE;
use IEEE.std_logic_1164.all;

entity DFF_N is
    generic( N : integer := 4);
    port(
        D           : in std_logic_vector(N-1 downto 0);
        clk, rst    : in std_logic;
        -- enable
        en          : in std_logic;
        Q           : out std_logic_vector(N-1 downto 0)
        );
end DFF_N;

--------------------------------------------------------------------------------
-- architecture structural
--------------------------------------------------------------------------------
architecture struct of DFF_N is
begin
  -- Here, the process is sensitive to the RST and CLK signals,
  -- Asynchronous reset
  dff_proc: process(clk,rst)
  begin
    if(rst = '0') then
      Q  <= (others => '0');
    elsif(rising_edge(clk)) then
      if(en = '1') then
          Q <= D;
      end if;
    end if;

  end process dff_proc;

end struct;

playground/src/adder/RCA_N/FA.vhd
library ieee;
use ieee.std_logic_1164.ALL;
---------------------------------------------------------------------------------------------
-- FullAdder Implementation
-- Implementation of Full Adder using structural design pattern (gate_Level)
-- Testbench is Included under the name FA_tb
-- For Modularity this module is reused to create a Ripple Carry Adder RCA4
--          This is achieved by redefining the FA component in RCA4.vhd file
---------------------------------------------------------------------------------------------
entity FA is
  port (
    A, B, cin : in std_logic;
    s, cout   : out std_logic);
end FA;


architecture structure of FA is
begin
    s <= A XOR B XOR cin;
    cout <= (A AND B) OR (cin AND A) OR (cin AND B);

end structure;

playground/src/counter/RCA_N.vhd
--------------------------------------------------------------------------------
-- N-bits (Generic) Ripple Carry Adder: RCA_N.vhd
--------------------------------------------------------------------------------

library IEEE;
use IEEE.std_logic_1164.all;

entity RCA_N is
    generic ( Nbit : positive := 4); -- positive(unsigned) or integer
    port (
        A,B : in  std_logic_vector(Nbit-1 downto 0);
        cin : in  std_logic;
        s   : out std_logic_vector(Nbit-1 downto 0);
        cout: out std_logic);
end RCA_N;


architecture structure of RCA_N is
-- Define a component to describe the desgin relation in FA.vhd to be used here in
-- RCA_N.vhd generic ripple carry adder
    component FA
        port (
            A     : in  std_logic;
            B     : in  std_logic;
            cin   : in  std_logic;
            s     : out std_logic;
            cout  : out std_logic);
  end component;

  -- In 4-RCA we used to create 3 signals for each carry propagate from each flip flip
  -- signal c0,c1,c2 : std_logic;
  -- since, here it's a N-RCA so we create a vector 
  signal c : std_ulogic_vector(Nbit downto 0);

begin

rca_n_proc : for i in 0 to Nbit-1 generate

    fa_i: FA port map (
        A     => A(i),
        B     => B(i),
        --
        cin   => cin,
        s     => s(i),
        cout  => c(i)
        );
    end generate rca_n_proc;

end structure;

playground/src/counter/counter.vhd
library ieee;
use ieee.std_logic_1164.all;
-------------------------------------------------------------------
  -- Counter entity
  -- @brief
  -- N-Bit Accumlator: [Phase Accumlator ]
  -- counter.vhd is based on DFF (F-FlipFlop) and FA (FullAdder)
  -- d is the frequency word input to the counter (N-Bit Accumlator)
  -- q is the N-Bit output which is feeded back to the N-Bit FullAdder
-------------------------------------------------------------------

entity counter is
  generic( N : integer := 4);
  port(
    d         : in std_logic_vector(N-1 downto 0);
    q         : out std_logic_vector(N-1 downto 0);
    clk,rst,en: in std_logic);
end counter;



-------------------------------------------------------------------
  -- Counter architecture
  -- @brief
-- Define 2 signals to hold the output vector of both DFF and RCA
--    Interconnection 1: [Between FA and DFF]     @fa_out
--    Interconnection 2: [Between DFF and output] @dff_out
-- Define 2 components to describe the embedded modules DFF and RCA (FA)
-------------------------------------------------------------------

architecture struct of counter is

signal dff_out  : std_logic_vector(N-1 downto 0);
signal fa_out : std_logic_vector(N-1 downto 0);

-------------------------------------------------------------------
-- DFF and RCA Components declaration
-------------------------------------------------------------------

component DFF_N is
    generic( N : integer := 4);
    port(
        D           : in std_logic_vector(N-1 downto 0);
        clk, rst    : in std_logic;
        -- enable
        en          : in std_logic;
        Q           : out std_logic_vector(N-1 downto 0)
        );
end component;


component RCA_N is
    generic ( Nbit : positive := 4); -- positive(unsigned) or integer
    port (
        A,B : in  std_logic_vector(Nbit-1 downto 0);
        cin : in  std_logic;
        s   : out std_logic_vector(Nbit-1 downto 0);
        cout: out std_logic);
end component;


   begin

  RCA_N_MAP :  RCA_N
      generic map(Nbit => N)
      port map(
       -- Input of the full-adder A, B and cin
        A     => d,       -- d is the frequency word (input of the counter)
        B     => dff_out, -- as dff_out is feeded back to the FA
        cin   => '0',
        s     => fa_out,
        cout  => open);

  DFF_N_MAP : DFF_N
      generic map(N => N)
      port map(
        d     => fa_out,
        clk   => clk,
        rst   => rst,
        en    => en,
        q     => dff_out);
  	    q <= dff_out;

end struct;

playground/src/counter/counter_tb.vhd
library ieee;
use ieee.std_logic_1164.all;
-------------------------------------------------------------------
  -- Counter Testbench
-------------------------------------------------------------------

entity counter_tb is
end counter_tb;

-------------------------------------------------------------------
  -- Counter architecture
-------------------------------------------------------------------

architecture struct of counter_tb is

-------------------------------------------------------------------
-- Testbench constants
-------------------------------------------------------------------
constant T_CLK   : time := 10 ns; -- Clock period
constant T_RESET : time := 25 ns; -- Period before the reset deassertion
constant N_TB	: natural := 3;	  -- Generic constant definition
-------------------------------------------------------------------
-- Testbench signals
-------------------------------------------------------------------
signal clk_tb : std_logic := '0'; -- clock signal, intialized to '0'
signal rst_tb  : std_logic := '0'; -- reset signal
signal d_tb    : std_logic_vector(N_TB-1 downto 0);        -- d signal to connect to the d port of the component
signal q_tb    : std_logic_vector(N_TB-1 downto 0);        -- q signal to connect to the q port of the component
signal en_tb	: std_logic := '1'; -- enable signal to connect to the en input port
signal end_sim : std_logic := '1'; -- signal to use to stop the simulation when there is nothing else to test



component counter is
  generic( N : integer := 4);
  port(
    d         : in std_logic_vector(N-1 downto 0);
    q         : out std_logic_vector(N-1 downto 0);
    clk,rst,en: in std_logic);
end component;


   begin
   clk_tb <= (not(clk_tb) and end_sim) after T_CLK / 2;
   rst_tb <= '1' after T_RESET;
  counter_map :  counter
      generic map(N => N_tb)
      port map(
       -- Input of the full-adder A, B and cin
        d     => d_tb,       -- d is the frequency word (input of the counter)
        clk   => clk_tb,
        rst   => rst_tb,
        en		=> en_tb,
        q     => open
        );
-------------------------------------------------------------------
-- Start Testing process
   -- process used to make the testbench signals change
   -- synchronously with the rising edge of the clock
-------------------------------------------------------------------

  counter_proc: process(clk_tb, rst_tb)
    -- variable used to count the clock cycle after the reset
    variable t : integer := 0;
    begin
      if(rst_tb = '0') then
        d_tb <= (others => '0');
        en_tb <= '1';
        t := 0;
      elsif(rising_edge(clk_tb)) then
      -- specifying the input d_tb and end_sim depending
      -- on the value of t ( and so on the number of the passed clock cycles).
        case(t) is
        -- count 1 by 1
        when 1 => d_tb <= "001"; 	-- not generic. If you change N_TB you have to fix the length of the test vector

        -- count 2 by 2
        when 8 => d_tb <= "010";	-- not generic. If you change N_TB you have to fix the length of the test vector

        -- add here more cases to test

        when 14 => end_sim <= '0'; -- This command stops the simulation when t = 10
        when others => null; -- Specifying that nothing happens in the other cases

        end case;
        t := t + 1; -- the variable is updated exactly here (try to move this statement before the "case(t) is" one and watch the difference in the simulation)
        end if;

        end process;


end struct;

playground/src/counter/cnt.vcd
$date
  Sun Apr 28 16:14:12 2019
$end
$version
  GHDL v0
$end
$timescale
  1 fs
$end
$scope module standard $end
$upscope $end
$scope module std_logic_1164 $end
$upscope $end
$scope module counter_tb $end
$var reg 1 ! clk_tb $end
$var reg 1 " rst_tb $end
$var reg 3 # d_tb[2:0] $end
$var reg 3 $ q_tb[2:0] $end
$var reg 1 % en_tb $end
$var reg 1 & end_sim $end
$scope module counter_map $end
$var reg 3 ' d[2:0] $end
$var reg 3 ( q[2:0] $end
$var reg 1 ) clk $end
$var reg 1 * rst $end
$var reg 1 + en $end
$var reg 3 , dff_out[2:0] $end
$var reg 3 - fa_out[2:0] $end
$scope module rca_n_map $end
$var reg 3 . a[2:0] $end
$var reg 3 / b[2:0] $end
$var reg 1 0 cin $end
$var reg 3 1 s[2:0] $end
$var reg 1 2 cout $end
$var reg 4 3 c[3:0] $end
$scope module rca_n_proc(0) $end
$scope module fa_i $end
$var reg 1 4 a $end
$var reg 1 5 b $end
$var reg 1 6 cin $end
$var reg 1 7 s $end
$var reg 1 8 cout $end
$upscope $end
$upscope $end
$scope module rca_n_proc(1) $end
$scope module fa_i $end
$var reg 1 9 a $end
$var reg 1 : b $end
$var reg 1 ; cin $end
$var reg 1 < s $end
$var reg 1 = cout $end
$upscope $end
$upscope $end
$scope module rca_n_proc(2) $end
$scope module fa_i $end
$var reg 1 > a $end
$var reg 1 ? b $end
$var reg 1 @ cin $end
$var reg 1 A s $end
$var reg 1 B cout $end
$upscope $end
$upscope $end
$upscope $end
$scope module dff_n_map $end
$var reg 3 C d[2:0] $end
$var reg 1 D clk $end
$var reg 1 E rst $end
$var reg 1 F en $end
$var reg 3 G q[2:0] $end
$upscope $end
$upscope $end
$upscope $end
$enddefinitions $end
#0
0!
0"
b000 #
bUUU $
1%
1&
b000 '
b000 (
0)
0*
1+
b000 ,
b000 -
b000 .
b000 /
00
b000 1
U2
bU000 3
04
05
06
07
08
09
0:
0;
0<
0=
0>
0?
0@
0A
0B
b000 C
0D
0E
1F
b000 G
#5000000
1!
1)
1D
#10000000
0!
0)
0D
#15000000
1!
1)
1D
#20000000
0!
0)
0D
#25000000
1!
1"
1)
1*
1D
1E
#30000000
0!
0)
0D
#35000000
1!
b001 #
b001 '
1)
b001 -
b001 .
b001 1
14
17
b001 C
1D
#40000000
0!
0)
0D
#45000000
1!
b001 (
1)
b001 ,
b000 -
b001 /
b000 1
bU001 3
15
07
18
b000 C
1D
b001 G
#50000000
0!
0)
0D
#55000000
1!
b000 (
1)
b000 ,
b001 -
b000 /
b001 1
bU000 3
05
17
08
b001 C
1D
b000 G
#60000000
0!
0)
0D
#65000000
1!
b001 (
1)
b001 ,
b000 -
b001 /
b000 1
bU001 3
15
07
18
b000 C
1D
b001 G
#70000000
0!
0)
0D
#75000000
1!
b000 (
1)
b000 ,
b001 -
b000 /
b001 1
bU000 3
05
17
08
b001 C
1D
b000 G
#80000000
0!
0)
0D
#85000000
1!
b001 (
1)
b001 ,
b000 -
b001 /
b000 1
bU001 3
15
07
18
b000 C
1D
b001 G
#90000000
0!
0)
0D
#95000000
1!
b000 (
1)
b000 ,
b001 -
b000 /
b001 1
bU000 3
05
17
08
b001 C
1D
b000 G
#100000000
0!
0)
0D
#105000000
1!
b010 #
b010 '
b001 (
1)
b001 ,
b011 -
b010 .
b001 /
b011 1
04
15
19
1<
b011 C
1D
b001 G
#110000000
0!
0)
0D
#115000000
1!
b011 (
1)
b011 ,
b001 -
b011 /
b001 1
bU010 3
1:
0<
1=
b001 C
1D
b011 G
#120000000
0!
0)
0D
#125000000
1!
b001 (
1)
b001 ,
b011 -
b001 /
b011 1
bU000 3
0:
1<
0=
b011 C
1D
b001 G
#130000000
0!
0)
0D
#135000000
1!
b011 (
1)
b011 ,
b001 -
b011 /
b001 1
bU010 3
1:
0<
1=
b001 C
1D
b011 G
#140000000
0!
0)
0D
#145000000
1!
b001 (
1)
b001 ,
b011 -
b001 /
b011 1
bU000 3
0:
1<
0=
b011 C
1D
b001 G
#150000000
0!
0)
0D
#155000000
1!
b011 (
1)
b011 ,
b001 -
b011 /
b001 1
bU010 3
1:
0<
1=
b001 C
1D
b011 G
#160000000
0!
0)
0D
#165000000
1!
0&
b001 (
1)
b001 ,
b011 -
b001 /
b011 1
bU000 3
0:
1<
0=
b011 C
1D
b001 G
