playground/src/d-flipflop/DFF/DFF.vhd
--------------------------------------------------------------------------------
-- generic FlipFlop
--------------------------------------------------------------------------------

library IEEE;
use IEEE.std_logic_1164.all;

entity DFF is
  port(
    D, clk, rst   : in std_logic;
    Q             : out std_logic);
end DFF;

--------------------------------------------------------------------------------
-- architecture structural
--------------------------------------------------------------------------------
architecture beh of dff is
begin
  -- Here, the process is sensitive to the RST and CLK signals,
  -- Asynchronous reset
  i_dff: process(clk,rst)
  begin
    if rst='1' then
      Q <= '0';
    elsif (clk='1' and clk'event) then -- for the rising edge trigger the output
      Q <= D;
    end if;
  end process i_dff;

end beh;


--------------------------------------------------------------------------------
  -- NOTE
--------------------------------------------------------------------------------
--* If I use the Synchronous Reset; so everything will be sensitive to the clk
--* Therefore
--* process(clk)
--*begin
--*  if (clk='1' and clk'event)
--*    if rst='1' then
--*      Q <= '0';
--*    else
--*      Q <= D;
--*    end if;
--*  end if;
--* end process;
--------------------------------------------------------------------------------

playground/src/d-flipflop/DFF/DFF_tb.vhd
--------------------------------------------------------------------------------
-- D-FlipFlop FlipFlop
--------------------------------------------------------------------------------

library IEEE;
use IEEE.std_logic_1164.all;

entity DFF_tb is
end DFF_tb;

--------------------------------------------------------------------------------
-- architecture structural
--------------------------------------------------------------------------------
architecture beh of DFF_tb is

  component DFF
    port (
      D,clk, rst    : in  std_logic;
      Q             : out std_logic
    );
  end component DFF;

  signal clk           : std_logic := '0';
  signal rst           : std_logic := '1';
  signal clk_go        : std_logic;

  signal D             : std_logic;
  constant clk_period  : time := 100 ns;

begin

-- Define Clock process for testbench
  -- clk_process :process
  -- begin
  -- clk <= '0';
  -- wait for clk_period/2;
  -- clk <= '1';
  -- wait for clk_period/2;
  -- end process;
-- OR in one LINE
  clk <= not clk after clk_period/2 when clk_go='1' else '0';

  dut: DFF
  port map (
    clk     => clk    ,
    rst     => rst    ,
    D       => D      ,
    Q       => open
  );


  -- Define Test Vectors
  stim_proc: process
  begin
    rst     <= '1';
    D       <= '0';
    clk_go  <= '1';

    wait for 100 ns;
    rst     <= '0';
    wait until rising_edge(clk);
    D       <= '1';

    wait until rising_edge(clk);
    wait until rising_edge(clk);
    wait until rising_edge(clk);
    D       <= '0';

    wait until rising_edge(clk);
    wait until rising_edge(clk);
    D       <= '1';

    wait until rising_edge(clk);
    wait for 100 ns;
    rst     <= '1';
    wait for 100 ns;
    clk_go  <= '0';
    wait;

  end process stim_proc;

end beh;


-- Another way to define the testVector.
  -- Define Test Vectors
  --  rst     <= '1';
  --  D       <= '0';
  --  wait for 100 ns;
  --  rst     <= '1';
  --  D       <= '1';
  --  wait for 100 ns;
  --  rst     <= '0';
  --  D       <= '1';
  --  wait for 100 ns;
  --  rst     <= '0';
  --  D       <= '0';
  --  wait;
  -- end process stim_proc;

playground/src/d-flipflop/DFF/dff.vcd
$date
  Sun Apr 28 14:46:09 2019
$end
$version
  GHDL v0
$end
$timescale
  1 fs
$end
$scope module standard $end
$upscope $end
$scope module std_logic_1164 $end
$upscope $end
$scope module dff_tb $end
$var reg 1 ! clk $end
$var reg 1 " rst $end
$var reg 1 # clk_go $end
$var reg 1 $ d $end
$scope module dut $end
$var reg 1 % d $end
$var reg 1 & clk $end
$var reg 1 ' rst $end
$var reg 1 ( q $end
$upscope $end
$upscope $end
$enddefinitions $end
#0
0!
1"
1#
0$
0%
0&
1'
0(
#50000000
1!
1&
#100000000
0!
0"
0&
0'
#150000000
1!
1$
1%
1&
#200000000
0!
0&
#250000000
1!
1&
1(
#300000000
0!
0&
#350000000
1!
1&
#400000000
0!
0&
#450000000
1!
0$
0%
1&
#500000000
0!
0&
#550000000
1!
1&
0(
#600000000
0!
0&
#650000000
1!
1$
1%
1&
#700000000
0!
0&
#750000000
1!
1&
1(
#800000000
0!
0&
#850000000
1!
1"
1&
1'
0(
