playground/src/adder/RCA_N/FA.vhd
library ieee;
use ieee.std_logic_1164.ALL;
---------------------------------------------------------------------------------------------
-- FullAdder Implementation
-- Implementation of Full Adder using structural design pattern (gate_Level)
-- Testbench is Included under the name FA_tb
-- For Modularity this module is reused to create a Ripple Carry Adder RCA4
--          This is achieved by redefining the FA component in RCA4.vhd file
---------------------------------------------------------------------------------------------
entity FA is
  port (
    A, B, cin : in std_logic;
    s, cout   : out std_logic);
end FA;


architecture structure of FA is
begin
    s <= A XOR B XOR cin;
    cout <= (A AND B) OR (cin AND A) OR (cin AND B);

end structure;

playground/src/adder/RCA_N/RCA_N.vhd
--------------------------------------------------------------------------------
-- N-bits (Generic) Ripple Carry Adder: RCA_N.vhd
--------------------------------------------------------------------------------

library IEEE;
use IEEE.std_logic_1164.all;

entity RCA_N is
    generic ( Nbit : positive := 4); -- positive(unsigned) or integer
    port (
        A,B : in  std_logic_vector(Nbit-1 downto 0);
        cin : in  std_logic;
        s   : out std_logic_vector(Nbit-1 downto 0);
        cout: out std_logic);
end RCA_N;


architecture structure of RCA_N is
-- Define a component to describe the desgin relation in FA.vhd to be used here in
-- RCA_N.vhd generic ripple carry adder
    component FA
        port (
            A     : in  std_logic;
            B     : in  std_logic;
            cin   : in  std_logic;
            s     : out std_logic;
            cout  : out std_logic);
  end component;

  -- In 4-RCA we used to create 3 signals for each carry propagate from each Adder
  -- But since we will define the interconnection PLUS input and output so we have 5 signals
  -- signal c0,c1,c2,c3,c4 : std_logic;
  -- since, here it's a N-RCA so we create a vector
  -- 3 signals for the interconnection between FA modules
  -- PLUS input and output [in->FA0->FA1->FA2->FA3->]
  signal c : std_ulogic_vector(Nbit downto 0);

begin

    -- Input carry mapping
    c(0) <= cin;
    -- Output carry mapping
    cout  <= c(Nbit);
rca_n_proc : for i in 0 to Nbit-1 generate

    fa_i: FA port map (
        A     => A(i),
        B     => B(i),
        --
        cin   => c(i),
        s     => s(i),
        cout  => c(i+1)
        );
    end generate rca_n_proc;

end structure;

playground/src/adder/RCA_N/RCA_N_tb.vhd
-----------------------------------
-- N Bit Ripple Carry Adder
-----------------------------------
library IEEE;
use IEEE.std_logic_1164.all;
use IEEE.numeric_std.all;

-- entity
entity RCA_N_tb is
end RCA_N_tb;

architecture data_flow of RCA_N_tb is

  ----------------------------------------
    -- Component to test DUT
    -- HINT: Must be named as tested entity
  ----------------------------------------
  component RCA_N
    generic (Nbit : positive := 4);
    port (
      A,B     : in  std_logic_vector(Nbit-1 downto 0);
      cin     : in  std_logic;
      s       : out std_logic_vector(Nbit-1 downto 0);
      cout    : out std_logic
    );
  end component;

  ----------------------------------------
    -- Testbench constant declaration
  ----------------------------------------
    -- Generic constant definition
    constant Nbit : positive := 4;
    -- signals for mapping the component variables to test variables (local copy)
    signal A_tb, B_tb     : std_logic_vector(Nbit-1 downto 0);
    signal cin_tb         : std_logic;

  ----------------------------------------
    -- Start Port Mapping
    -- linking the gates with the testbench
    -- signals for the test
  ----------------------------------------
begin

  dut: RCA_N
    generic map (
        Nbit => Nbit
    )
    port map (
        A     => A_tb   ,
        B     => B_tb   ,
        cin   => cin_tb ,
        s     => open   , -- I can use signals or make it only open
        cout  => open  -- I can use signals or make it only open
    );

  ----------------------------------------
    -- Start Testing Process
  ----------------------------------------
  -- ******************************************************
  -- * Even if rippleCarryAdder is a pure combinational circuit
  -- * it is possible to use a clock signal within the tb
  -- * just for keep trace of the execution time of the
  -- * simulation and to provide input vectors to the DUT
  -- * It's not a good behavior to use a loop to define the
  -- * testvectors
  -- * but WHO CARES!!
  -- ******************************************************

  -- process used to make the testbench signals change synchronously with the rising edge of the clock

  stim_proc: process
  -- variable used to count the clock cycle after the reset
  begin

    --A_tb <= (others => '0');
    --B_tb <= (others => '0');
    A_tb <= "0000";
    B_tb <= "0000";
    cin_tb <= '0';

    wait for 100 ns;
    -----------------------------------------------
    -- Since this is a 4-Bit Ripple Carry Adder
    -- We have 2pow(4):= 16 test vecotors
    -- It's not good to create the test vectors using loop but its better than manually define them
    -----------------------------------------------
    -- generate 16 test vectors considering cin:=0;

    for i in 0 to 2**Nbit-1 loop
      A_tb   <= std_logic_vector(TO_SIGNED(i,Nbit));
      for j in 0 to 2**Nbit-1 loop
        B_tb   <= std_logic_vector(TO_SIGNED(j,Nbit));
        wait for 100 ns;
      end loop;
    end loop;

    cin_tb <= '1';
    -- generate 16 test vectors considering cin:=1;
    for i in 0 to 2**Nbit-1 loop
      A_tb   <= std_logic_vector(TO_SIGNED(i,Nbit));
      for j in 0 to 2**Nbit-1 loop
        B_tb   <= std_logic_vector(TO_SIGNED(j,Nbit));
        wait for 100 ns;
      end loop;
    end loop;

    wait;
    end process stim_proc;


end data_flow;

playground/src/adder/RCA_N/RCA_N.vcd
$date
  Sun Apr 28 13:57:47 2019
$end
$version
  GHDL v0
$end
$timescale
  1 fs
$end
$scope module standard $end
$upscope $end
$scope module std_logic_1164 $end
$upscope $end
$scope module numeric_std $end
$upscope $end
$scope module rca_n_tb $end
$var reg 4 ! a_tb[3:0] $end
$var reg 4 " b_tb[3:0] $end
$var reg 1 # cin_tb $end
$scope module dut $end
$var reg 4 $ a[3:0] $end
$var reg 4 % b[3:0] $end
$var reg 1 & cin $end
$var reg 4 ' s[3:0] $end
$var reg 1 ( cout $end
$var reg 5 ) c[4:0] $end
$scope module rca_n_proc(0) $end
$scope module fa_i $end
$var reg 1 * a $end
$var reg 1 + b $end
$var reg 1 , cin $end
$var reg 1 - s $end
$var reg 1 . cout $end
$upscope $end
$upscope $end
$scope module rca_n_proc(1) $end
$scope module fa_i $end
$var reg 1 / a $end
$var reg 1 0 b $end
$var reg 1 1 cin $end
$var reg 1 2 s $end
$var reg 1 3 cout $end
$upscope $end
$upscope $end
$scope module rca_n_proc(2) $end
$scope module fa_i $end
$var reg 1 4 a $end
$var reg 1 5 b $end
$var reg 1 6 cin $end
$var reg 1 7 s $end
$var reg 1 8 cout $end
$upscope $end
$upscope $end
$scope module rca_n_proc(3) $end
$scope module fa_i $end
$var reg 1 9 a $end
$var reg 1 : b $end
$var reg 1 ; cin $end
$var reg 1 < s $end
$var reg 1 = cout $end
$upscope $end
$upscope $end
$upscope $end
$upscope $end
$enddefinitions $end
#0
b0000 !
b0000 "
0#
b0000 $
b0000 %
0&
b0000 '
0(
b00000 )
0*
0+
0,
0-
0.
0/
00
01
02
03
04
05
06
07
08
09
0:
0;
0<
0=
#100000000
#200000000
b0001 "
b0001 %
b0001 '
1+
1-
#300000000
b0010 "
b0010 %
b0010 '
0+
0-
10
12
#400000000
b0011 "
b0011 %
b0011 '
1+
1-
#500000000
b0100 "
b0100 %
b0100 '
0+
0-
00
02
15
17
#600000000
b0101 "
b0101 %
b0101 '
1+
1-
#700000000
b0110 "
b0110 %
b0110 '
0+
0-
10
12
#800000000
b0111 "
b0111 %
b0111 '
1+
1-
#900000000
b1000 "
b1000 %
b1000 '
0+
0-
00
02
05
07
1:
1<
#1000000000
b1001 "
b1001 %
b1001 '
1+
1-
#1100000000
b1010 "
b1010 %
b1010 '
0+
0-
10
12
#1200000000
b1011 "
b1011 %
b1011 '
1+
1-
#1300000000
b1100 "
b1100 %
b1100 '
0+
0-
00
02
15
17
#1400000000
b1101 "
b1101 %
b1101 '
1+
1-
#1500000000
b1110 "
b1110 %
b1110 '
0+
0-
10
12
#1600000000
b1111 "
b1111 %
b1111 '
1+
1-
#1700000000
b0001 !
b0000 "
b0001 $
b0000 %
b0001 '
1*
0+
00
02
05
07
0:
0<
#1800000000
b0001 "
b0001 %
b0010 '
b00010 )
1+
0-
1.
11
12
#1900000000
b0010 "
b0010 %
b0011 '
b00000 )
0+
1-
0.
10
01
12
03
06
07
#2000000000
b0011 "
b0011 %
b0100 '
b00110 )
1+
0-
1.
11
02
13
16
17
#2100000000
b0100 "
b0100 %
b0101 '
b00000 )
0+
1-
0.
00
01
02
03
15
06
17
08
0;
0<
#2200000000
b0101 "
b0101 %
b0110 '
b00010 )
1+
0-
1.
11
12
#2300000000
b0110 "
b0110 %
b0111 '
b00000 )
0+
1-
0.
10
01
12
03
06
17
08
0;
0<
#2400000000
b0111 "
b0111 %
b1000 '
b01110 )
1+
0-
1.
11
02
13
16
07
18
1;
1<
#2500000000
b1000 "
b1000 %
b1001 '
0(
b00000 )
0+
1-
0.
00
01
02
03
05
06
07
08
1:
0;
1<
0=
#2600000000
b1001 "
b1001 %
b1010 '
b00010 )
1+
0-
1.
11
12
#2700000000
b1010 "
b1010 %
b1011 '
b00000 )
0+
1-
0.
10
01
12
03
06
07
#2800000000
b1011 "
b1011 %
b1100 '
b00110 )
1+
0-
1.
11
02
13
16
17
#2900000000
b1100 "
b1100 %
b1101 '
0(
b00000 )
0+
1-
0.
00
01
02
03
15
06
17
08
0;
1<
0=
#3000000000
b1101 "
b1101 %
b1110 '
b00010 )
1+
0-
1.
11
12
#3100000000
b1110 "
b1110 %
b1111 '
0(
b00000 )
0+
1-
0.
10
01
12
03
06
17
08
0;
1<
0=
#3200000000
b1111 "
b1111 %
b0000 '
1(
b11110 )
1+
0-
1.
11
02
13
16
07
18
1;
0<
1=
#3300000000
b0010 !
b0000 "
b0010 $
b0000 %
b0010 '
0(
b00000 )
0*
0+
0.
1/
00
01
12
03
05
06
07
08
0:
0;
0<
0=
#3400000000
b0001 "
b0001 %
b0011 '
1+
1-
#3500000000
b0010 "
b0010 %
b0100 '
b00100 )
0+
0-
10
02
13
16
17
#3600000000
b0011 "
b0011 %
b0101 '
1+
1-
#3700000000
b0100 "
b0100 %
b0110 '
b00000 )
0+
0-
00
12
03
15
06
17
08
0;
0<
#3800000000
b0101 "
b0101 %
b0111 '
1+
1-
#3900000000
b0110 "
b0110 %
b1000 '
b01100 )
0+
0-
10
02
13
16
07
18
1;
1<
#4000000000
b0111 "
b0111 %
b1001 '
1+
1-
#4100000000
b1000 "
b1000 %
b1010 '
0(
b00000 )
0+
0-
00
12
03
05
06
07
08
1:
0;
1<
0=
#4200000000
b1001 "
b1001 %
b1011 '
1+
1-
#4300000000
b1010 "
b1010 %
b1100 '
b00100 )
0+
0-
10
02
13
16
17
#4400000000
b1011 "
b1011 %
b1101 '
1+
1-
#4500000000
b1100 "
b1100 %
b1110 '
0(
b00000 )
0+
0-
00
12
03
15
06
17
08
0;
1<
0=
#4600000000
b1101 "
b1101 %
b1111 '
1+
1-
#4700000000
b1110 "
b1110 %
b0000 '
1(
b11100 )
0+
0-
10
02
13
16
07
18
1;
0<
1=
#4800000000
b1111 "
b1111 %
b0001 '
1+
1-
#4900000000
b0011 !
b0000 "
b0011 $
b0000 %
b0011 '
0(
b00000 )
1*
0+
00
12
03
05
06
07
08
0:
0;
0<
0=
#5000000000
b0001 "
b0001 %
b0100 '
b00110 )
1+
0-
1.
11
02
13
16
17
#5100000000
b0010 "
b0010 %
b0101 '
b00100 )
0+
1-
0.
10
01
02
#5200000000
b0011 "
b0011 %
b0110 '
b00110 )
1+
0-
1.
11
12
#5300000000
b0100 "
b0100 %
b0111 '
b00000 )
0+
1-
0.
00
01
12
03
15
06
17
08
0;
0<
#5400000000
b0101 "
b0101 %
b1000 '
b01110 )
1+
0-
1.
11
02
13
16
07
18
1;
1<
#5500000000
b0110 "
b0110 %
b1001 '
b01100 )
0+
1-
0.
10
01
02
#5600000000
b0111 "
b0111 %
b1010 '
b01110 )
1+
0-
1.
11
12
#5700000000
b1000 "
b1000 %
b1011 '
0(
b00000 )
0+
1-
0.
00
01
12
03
05
06
07
08
1:
0;
1<
0=
#5800000000
b1001 "
b1001 %
b1100 '
b00110 )
1+
0-
1.
11
02
13
16
17
#5900000000
b1010 "
b1010 %
b1101 '
b00100 )
0+
1-
0.
10
01
02
#6000000000
b1011 "
b1011 %
b1110 '
b00110 )
1+
0-
1.
11
12
#6100000000
b1100 "
b1100 %
b1111 '
0(
b00000 )
0+
1-
0.
00
01
12
03
15
06
17
08
0;
1<
0=
#6200000000
b1101 "
b1101 %
b0000 '
1(
b11110 )
1+
0-
1.
11
02
13
16
07
18
1;
0<
1=
#6300000000
b1110 "
b1110 %
b0001 '
b11100 )
0+
1-
0.
10
01
02
#6400000000
b1111 "
b1111 %
b0010 '
b11110 )
1+
0-
1.
11
12
#6500000000
b0100 !
b0000 "
b0100 $
b0000 %
b0100 '
0(
b00000 )
0*
0+
0.
0/
00
01
02
03
14
05
06
17
08
0:
0;
0<
0=
#6600000000
b0001 "
b0001 %
b0101 '
1+
1-
#6700000000
b0010 "
b0010 %
b0110 '
0+
0-
10
12
#6800000000
b0011 "
b0011 %
b0111 '
1+
1-
#6900000000
b0100 "
b0100 %
b1000 '
b01000 )
0+
0-
00
02
15
07
18
1;
1<
#7000000000
b0101 "
b0101 %
b1001 '
1+
1-
#7100000000
b0110 "
b0110 %
b1010 '
0+
0-
10
12
#7200000000
b0111 "
b0111 %
b1011 '
1+
1-
#7300000000
b1000 "
b1000 %
b1100 '
0(
b00000 )
0+
0-
00
02
05
17
08
1:
0;
1<
0=
#7400000000
b1001 "
b1001 %
b1101 '
1+
1-
#7500000000
b1010 "
b1010 %
b1110 '
0+
0-
10
12
#7600000000
b1011 "
b1011 %
b1111 '
1+
1-
#7700000000
b1100 "
b1100 %
b0000 '
1(
b11000 )
0+
0-
00
02
15
07
18
1;
0<
1=
#7800000000
b1101 "
b1101 %
b0001 '
1+
1-
#7900000000
b1110 "
b1110 %
b0010 '
0+
0-
10
12
#8000000000
b1111 "
b1111 %
b0011 '
1+
1-
#8100000000
b0101 !
b0000 "
b0101 $
b0000 %
b0101 '
0(
b00000 )
1*
0+
00
02
05
17
08
0:
0;
0<
0=
#8200000000
b0001 "
b0001 %
b0110 '
b00010 )
1+
0-
1.
11
12
#8300000000
b0010 "
b0010 %
b0111 '
b00000 )
0+
1-
0.
10
01
12
03
06
17
08
0;
0<
#8400000000
b0011 "
b0011 %
b1000 '
b01110 )
1+
0-
1.
11
02
13
16
07
18
1;
1<
#8500000000
b0100 "
b0100 %
b1001 '
b01000 )
0+
1-
0.
00
01
02
03
15
06
07
#8600000000
b0101 "
b0101 %
b1010 '
b01010 )
1+
0-
1.
11
12
#8700000000
b0110 "
b0110 %
b1011 '
b01000 )
0+
1-
0.
10
01
12
03
06
07
#8800000000
b0111 "
b0111 %
b1100 '
b01110 )
1+
0-
1.
11
02
13
16
17
#8900000000
b1000 "
b1000 %
b1101 '
0(
b00000 )
0+
1-
0.
00
01
02
03
05
06
17
08
1:
0;
1<
0=
#9000000000
b1001 "
b1001 %
b1110 '
b00010 )
1+
0-
1.
11
12
#9100000000
b1010 "
b1010 %
b1111 '
0(
b00000 )
0+
1-
0.
10
01
12
03
06
17
08
0;
1<
0=
#9200000000
b1011 "
b1011 %
b0000 '
1(
b11110 )
1+
0-
1.
11
02
13
16
07
18
1;
0<
1=
#9300000000
b1100 "
b1100 %
b0001 '
b11000 )
0+
1-
0.
00
01
02
03
15
06
07
#9400000000
b1101 "
b1101 %
b0010 '
b11010 )
1+
0-
1.
11
12
#9500000000
b1110 "
b1110 %
b0011 '
b11000 )
0+
1-
0.
10
01
12
03
06
07
#9600000000
b1111 "
b1111 %
b0100 '
b11110 )
1+
0-
1.
11
02
13
16
17
#9700000000
b0110 !
b0000 "
b0110 $
b0000 %
b0110 '
0(
b00000 )
0*
0+
0.
1/
00
01
12
03
05
06
17
08
0:
0;
0<
0=
#9800000000
b0001 "
b0001 %
b0111 '
1+
1-
#9900000000
b0010 "
b0010 %
b1000 '
b01100 )
0+
0-
10
02
13
16
07
18
1;
1<
#10000000000
b0011 "
b0011 %
b1001 '
1+
1-
#10100000000
b0100 "
b0100 %
b1010 '
b01000 )
0+
0-
00
12
03
15
06
07
#10200000000
b0101 "
b0101 %
b1011 '
1+
1-
#10300000000
b0110 "
b0110 %
b1100 '
b01100 )
0+
0-
10
02
13
16
17
#10400000000
b0111 "
b0111 %
b1101 '
1+
1-
#10500000000
b1000 "
b1000 %
b1110 '
0(
b00000 )
0+
0-
00
12
03
05
06
17
08
1:
0;
1<
0=
#10600000000
b1001 "
b1001 %
b1111 '
1+
1-
#10700000000
b1010 "
b1010 %
b0000 '
1(
b11100 )
0+
0-
10
02
13
16
07
18
1;
0<
1=
#10800000000
b1011 "
b1011 %
b0001 '
1+
1-
#10900000000
b1100 "
b1100 %
b0010 '
b11000 )
0+
0-
00
12
03
15
06
07
#11000000000
b1101 "
b1101 %
b0011 '
1+
1-
#11100000000
b1110 "
b1110 %
b0100 '
b11100 )
0+
0-
10
02
13
16
17
#11200000000
b1111 "
b1111 %
b0101 '
1+
1-
#11300000000
b0111 !
b0000 "
b0111 $
b0000 %
b0111 '
0(
b00000 )
1*
0+
00
12
03
05
06
17
08
0:
0;
0<
0=
#11400000000
b0001 "
b0001 %
b1000 '
b01110 )
1+
0-
1.
11
02
13
16
07
18
1;
1<
#11500000000
b0010 "
b0010 %
b1001 '
b01100 )
0+
1-
0.
10
01
02
#11600000000
b0011 "
b0011 %
b1010 '
b01110 )
1+
0-
1.
11
12
#11700000000
b0100 "
b0100 %
b1011 '
b01000 )
0+
1-
0.
00
01
12
03
15
06
07
#11800000000
b0101 "
b0101 %
b1100 '
b01110 )
1+
0-
1.
11
02
13
16
17
#11900000000
b0110 "
b0110 %
b1101 '
b01100 )
0+
1-
0.
10
01
02
#12000000000
b0111 "
b0111 %
b1110 '
b01110 )
1+
0-
1.
11
12
#12100000000
b1000 "
b1000 %
b1111 '
0(
b00000 )
0+
1-
0.
00
01
12
03
05
06
17
08
1:
0;
1<
0=
#12200000000
b1001 "
b1001 %
b0000 '
1(
b11110 )
1+
0-
1.
11
02
13
16
07
18
1;
0<
1=
#12300000000
b1010 "
b1010 %
b0001 '
b11100 )
0+
1-
0.
10
01
02
#12400000000
b1011 "
b1011 %
b0010 '
b11110 )
1+
0-
1.
11
12
#12500000000
b1100 "
b1100 %
b0011 '
b11000 )
0+
1-
0.
00
01
12
03
15
06
07
#12600000000
b1101 "
b1101 %
b0100 '
b11110 )
1+
0-
1.
11
02
13
16
17
#12700000000
b1110 "
b1110 %
b0101 '
b11100 )
0+
1-
0.
10
01
02
#12800000000
b1111 "
b1111 %
b0110 '
b11110 )
1+
0-
1.
11
12
#12900000000
b1000 !
b0000 "
b1000 $
b0000 %
b1000 '
0(
b00000 )
0*
0+
0.
0/
00
01
02
03
04
05
06
07
08
19
0:
0;
1<
0=
#13000000000
b0001 "
b0001 %
b1001 '
1+
1-
#13100000000
b0010 "
b0010 %
b1010 '
0+
0-
10
12
#13200000000
b0011 "
b0011 %
b1011 '
1+
1-
#13300000000
b0100 "
b0100 %
b1100 '
0+
0-
00
02
15
17
#13400000000
b0101 "
b0101 %
b1101 '
1+
1-
#13500000000
b0110 "
b0110 %
b1110 '
0+
0-
10
12
#13600000000
b0111 "
b0111 %
b1111 '
1+
1-
#13700000000
b1000 "
b1000 %
b0000 '
1(
b10000 )
0+
0-
00
02
05
07
1:
0<
1=
#13800000000
b1001 "
b1001 %
b0001 '
1+
1-
#13900000000
b1010 "
b1010 %
b0010 '
0+
0-
10
12
#14000000000
b1011 "
b1011 %
b0011 '
1+
1-
#14100000000
b1100 "
b1100 %
b0100 '
0+
0-
00
02
15
17
#14200000000
b1101 "
b1101 %
b0101 '
1+
1-
#14300000000
b1110 "
b1110 %
b0110 '
0+
0-
10
12
#14400000000
b1111 "
b1111 %
b0111 '
1+
1-
#14500000000
b1001 !
b0000 "
b1001 $
b0000 %
b1001 '
0(
b00000 )
1*
0+
00
02
05
07
0:
1<
0=
#14600000000
b0001 "
b0001 %
b1010 '
b00010 )
1+
0-
1.
11
12
#14700000000
b0010 "
b0010 %
b1011 '
b00000 )
0+
1-
0.
10
01
12
03
06
07
#14800000000
b0011 "
b0011 %
b1100 '
b00110 )
1+
0-
1.
11
02
13
16
17
#14900000000
b0100 "
b0100 %
b1101 '
0(
b00000 )
0+
1-
0.
00
01
02
03
15
06
17
08
0;
1<
0=
#15000000000
b0101 "
b0101 %
b1110 '
b00010 )
1+
0-
1.
11
12
#15100000000
b0110 "
b0110 %
b1111 '
0(
b00000 )
0+
1-
0.
10
01
12
03
06
17
08
0;
1<
0=
#15200000000
b0111 "
b0111 %
b0000 '
1(
b11110 )
1+
0-
1.
11
02
13
16
07
18
1;
0<
1=
#15300000000
b1000 "
b1000 %
b0001 '
b10000 )
0+
1-
0.
00
01
02
03
05
06
07
08
1:
0;
0<
#15400000000
b1001 "
b1001 %
b0010 '
b10010 )
1+
0-
1.
11
12
#15500000000
b1010 "
b1010 %
b0011 '
b10000 )
0+
1-
0.
10
01
12
03
06
07
#15600000000
b1011 "
b1011 %
b0100 '
b10110 )
1+
0-
1.
11
02
13
16
17
#15700000000
b1100 "
b1100 %
b0101 '
b10000 )
0+
1-
0.
00
01
02
03
15
06
17
08
0;
0<
#15800000000
b1101 "
b1101 %
b0110 '
b10010 )
1+
0-
1.
11
12
#15900000000
b1110 "
b1110 %
b0111 '
b10000 )
0+
1-
0.
10
01
12
03
06
17
08
0;
0<
#16000000000
b1111 "
b1111 %
b1000 '
b11110 )
1+
0-
1.
11
02
13
16
07
18
1;
1<
#16100000000
b1010 !
b0000 "
b1010 $
b0000 %
b1010 '
0(
b00000 )
0*
0+
0.
1/
00
01
12
03
05
06
07
08
0:
0;
1<
0=
#16200000000
b0001 "
b0001 %
b1011 '
1+
1-
#16300000000
b0010 "
b0010 %
b1100 '
b00100 )
0+
0-
10
02
13
16
17
#16400000000
b0011 "
b0011 %
b1101 '
1+
1-
#16500000000
b0100 "
b0100 %
b1110 '
0(
b00000 )
0+
0-
00
12
03
15
06
17
08
0;
1<
0=
#16600000000
b0101 "
b0101 %
b1111 '
1+
1-
#16700000000
b0110 "
b0110 %
b0000 '
1(
b11100 )
0+
0-
10
02
13
16
07
18
1;
0<
1=
#16800000000
b0111 "
b0111 %
b0001 '
1+
1-
#16900000000
b1000 "
b1000 %
b0010 '
b10000 )
0+
0-
00
12
03
05
06
07
08
1:
0;
0<
#17000000000
b1001 "
b1001 %
b0011 '
1+
1-
#17100000000
b1010 "
b1010 %
b0100 '
b10100 )
0+
0-
10
02
13
16
17
#17200000000
b1011 "
b1011 %
b0101 '
1+
1-
#17300000000
b1100 "
b1100 %
b0110 '
b10000 )
0+
0-
00
12
03
15
06
17
08
0;
0<
#17400000000
b1101 "
b1101 %
b0111 '
1+
1-
#17500000000
b1110 "
b1110 %
b1000 '
b11100 )
0+
0-
10
02
13
16
07
18
1;
1<
#17600000000
b1111 "
b1111 %
b1001 '
1+
1-
#17700000000
b1011 !
b0000 "
b1011 $
b0000 %
b1011 '
0(
b00000 )
1*
0+
00
12
03
05
06
07
08
0:
0;
1<
0=
#17800000000
b0001 "
b0001 %
b1100 '
b00110 )
1+
0-
1.
11
02
13
16
17
#17900000000
b0010 "
b0010 %
b1101 '
b00100 )
0+
1-
0.
10
01
02
#18000000000
b0011 "
b0011 %
b1110 '
b00110 )
1+
0-
1.
11
12
#18100000000
b0100 "
b0100 %
b1111 '
0(
b00000 )
0+
1-
0.
00
01
12
03
15
06
17
08
0;
1<
0=
#18200000000
b0101 "
b0101 %
b0000 '
1(
b11110 )
1+
0-
1.
11
02
13
16
07
18
1;
0<
1=
#18300000000
b0110 "
b0110 %
b0001 '
b11100 )
0+
1-
0.
10
01
02
#18400000000
b0111 "
b0111 %
b0010 '
b11110 )
1+
0-
1.
11
12
#18500000000
b1000 "
b1000 %
b0011 '
b10000 )
0+
1-
0.
00
01
12
03
05
06
07
08
1:
0;
0<
#18600000000
b1001 "
b1001 %
b0100 '
b10110 )
1+
0-
1.
11
02
13
16
17
#18700000000
b1010 "
b1010 %
b0101 '
b10100 )
0+
1-
0.
10
01
02
#18800000000
b1011 "
b1011 %
b0110 '
b10110 )
1+
0-
1.
11
12
#18900000000
b1100 "
b1100 %
b0111 '
b10000 )
0+
1-
0.
00
01
12
03
15
06
17
08
0;
0<
#19000000000
b1101 "
b1101 %
b1000 '
b11110 )
1+
0-
1.
11
02
13
16
07
18
1;
1<
#19100000000
b1110 "
b1110 %
b1001 '
b11100 )
0+
1-
0.
10
01
02
#19200000000
b1111 "
b1111 %
b1010 '
b11110 )
1+
0-
1.
11
12
#19300000000
b1100 !
b0000 "
b1100 $
b0000 %
b1100 '
0(
b00000 )
0*
0+
0.
0/
00
01
02
03
14
05
06
17
08
0:
0;
1<
0=
#19400000000
b0001 "
b0001 %
b1101 '
1+
1-
#19500000000
b0010 "
b0010 %
b1110 '
0+
0-
10
12
#19600000000
b0011 "
b0011 %
b1111 '
1+
1-
#19700000000
b0100 "
b0100 %
b0000 '
1(
b11000 )
0+
0-
00
02
15
07
18
1;
0<
1=
#19800000000
b0101 "
b0101 %
b0001 '
1+
1-
#19900000000
b0110 "
b0110 %
b0010 '
0+
0-
10
12
#20000000000
b0111 "
b0111 %
b0011 '
1+
1-
#20100000000
b1000 "
b1000 %
b0100 '
b10000 )
0+
0-
00
02
05
17
08
1:
0;
0<
#20200000000
b1001 "
b1001 %
b0101 '
1+
1-
#20300000000
b1010 "
b1010 %
b0110 '
0+
0-
10
12
#20400000000
b1011 "
b1011 %
b0111 '
1+
1-
#20500000000
b1100 "
b1100 %
b1000 '
b11000 )
0+
0-
00
02
15
07
18
1;
1<
#20600000000
b1101 "
b1101 %
b1001 '
1+
1-
#20700000000
b1110 "
b1110 %
b1010 '
0+
0-
10
12
#20800000000
b1111 "
b1111 %
b1011 '
1+
1-
#20900000000
b1101 !
b0000 "
b1101 $
b0000 %
b1101 '
0(
b00000 )
1*
0+
00
02
05
17
08
0:
0;
1<
0=
#21000000000
b0001 "
b0001 %
b1110 '
b00010 )
1+
0-
1.
11
12
#21100000000
b0010 "
b0010 %
b1111 '
0(
b00000 )
0+
1-
0.
10
01
12
03
06
17
08
0;
1<
0=
#21200000000
b0011 "
b0011 %
b0000 '
1(
b11110 )
1+
0-
1.
11
02
13
16
07
18
1;
0<
1=
#21300000000
b0100 "
b0100 %
b0001 '
b11000 )
0+
1-
0.
00
01
02
03
15
06
07
#21400000000
b0101 "
b0101 %
b0010 '
b11010 )
1+
0-
1.
11
12
#21500000000
b0110 "
b0110 %
b0011 '
b11000 )
0+
1-
0.
10
01
12
03
06
07
#21600000000
b0111 "
b0111 %
b0100 '
b11110 )
1+
0-
1.
11
02
13
16
17
#21700000000
b1000 "
b1000 %
b0101 '
b10000 )
0+
1-
0.
00
01
02
03
05
06
17
08
1:
0;
0<
#21800000000
b1001 "
b1001 %
b0110 '
b10010 )
1+
0-
1.
11
12
#21900000000
b1010 "
b1010 %
b0111 '
b10000 )
0+
1-
0.
10
01
12
03
06
17
08
0;
0<
#22000000000
b1011 "
b1011 %
b1000 '
b11110 )
1+
0-
1.
11
02
13
16
07
18
1;
1<
#22100000000
b1100 "
b1100 %
b1001 '
b11000 )
0+
1-
0.
00
01
02
03
15
06
07
#22200000000
b1101 "
b1101 %
b1010 '
b11010 )
1+
0-
1.
11
12
#22300000000
b1110 "
b1110 %
b1011 '
b11000 )
0+
1-
0.
10
01
12
03
06
07
#22400000000
b1111 "
b1111 %
b1100 '
b11110 )
1+
0-
1.
11
02
13
16
17
#22500000000
b1110 !
b0000 "
b1110 $
b0000 %
b1110 '
0(
b00000 )
0*
0+
0.
1/
00
01
12
03
05
06
17
08
0:
0;
1<
0=
#22600000000
b0001 "
b0001 %
b1111 '
1+
1-
#22700000000
b0010 "
b0010 %
b0000 '
1(
b11100 )
0+
0-
10
02
13
16
07
18
1;
0<
1=
#22800000000
b0011 "
b0011 %
b0001 '
1+
1-
#22900000000
b0100 "
b0100 %
b0010 '
b11000 )
0+
0-
00
12
03
15
06
07
#23000000000
b0101 "
b0101 %
b0011 '
1+
1-
#23100000000
b0110 "
b0110 %
b0100 '
b11100 )
0+
0-
10
02
13
16
17
#23200000000
b0111 "
b0111 %
b0101 '
1+
1-
#23300000000
b1000 "
b1000 %
b0110 '
b10000 )
0+
0-
00
12
03
05
06
17
08
1:
0;
0<
#23400000000
b1001 "
b1001 %
b0111 '
1+
1-
#23500000000
b1010 "
b1010 %
b1000 '
b11100 )
0+
0-
10
02
13
16
07
18
1;
1<
#23600000000
b1011 "
b1011 %
b1001 '
1+
1-
#23700000000
b1100 "
b1100 %
b1010 '
b11000 )
0+
0-
00
12
03
15
06
07
#23800000000
b1101 "
b1101 %
b1011 '
1+
1-
#23900000000
b1110 "
b1110 %
b1100 '
b11100 )
0+
0-
10
02
13
16
17
#24000000000
b1111 "
b1111 %
b1101 '
1+
1-
#24100000000
b1111 !
b0000 "
b1111 $
b0000 %
b1111 '
0(
b00000 )
1*
0+
00
12
03
05
06
17
08
0:
0;
1<
0=
#24200000000
b0001 "
b0001 %
b0000 '
1(
b11110 )
1+
0-
1.
11
02
13
16
07
18
1;
0<
1=
#24300000000
b0010 "
b0010 %
b0001 '
b11100 )
0+
1-
0.
10
01
02
#24400000000
b0011 "
b0011 %
b0010 '
b11110 )
1+
0-
1.
11
12
#24500000000
b0100 "
b0100 %
b0011 '
b11000 )
0+
1-
0.
00
01
12
03
15
06
07
#24600000000
b0101 "
b0101 %
b0100 '
b11110 )
1+
0-
1.
11
02
13
16
17
#24700000000
b0110 "
b0110 %
b0101 '
b11100 )
0+
1-
0.
10
01
02
#24800000000
b0111 "
b0111 %
b0110 '
b11110 )
1+
0-
1.
11
12
#24900000000
b1000 "
b1000 %
b0111 '
b10000 )
0+
1-
0.
00
01
12
03
05
06
17
08
1:
0;
0<
#25000000000
b1001 "
b1001 %
b1000 '
b11110 )
1+
0-
1.
11
02
13
16
07
18
1;
1<
#25100000000
b1010 "
b1010 %
b1001 '
b11100 )
0+
1-
0.
10
01
02
