playground/src/adder/RCA_N/FA.vhd
library ieee;
use ieee.std_logic_1164.ALL;
---------------------------------------------------------------------------------------------
-- FullAdder Implementation
-- Implementation of Full Adder using structural design pattern (gate_Level)
-- Testbench is Included under the name FA_tb
-- For Modularity this module is reused to create a Ripple Carry Adder RCA4
--          This is achieved by redefining the FA component in RCA4.vhd file
---------------------------------------------------------------------------------------------
entity FA is
  port (
    A, B, cin : in std_logic;
    s, cout   : out std_logic);
end FA;


architecture structure of FA is
begin
    s <= A XOR B XOR cin;
    cout <= (A AND B) OR (cin AND A) OR (cin AND B);

end structure;

playground/src/adder/RCA4/RCA4.vhd
--------------------------------------------------------------------------------
-- 4-bits Ripple Carry Adder
--------------------------------------------------------------------------------

library IEEE;
use IEEE.std_logic_1164.all;

entity RCA4 is
  port (
    A       : in  std_logic_vector(3 downto 0);
    B       : in  std_logic_vector(3 downto 0);
    cin     : in  std_logic;
    s       : out std_logic_vector(3 downto 0);
    cout    : out std_logic);
end RCA4;

architecture struct of RCA4 is

  component FA 
    port (
      A     : in  std_logic;
      B     : in  std_logic;
      cin   : in  std_logic;
      s     : out std_logic;
      cout  : out std_logic);
  end component;

  signal c0,c1,c2 : std_logic;

begin

  fa0: fa
  port map (
    A     => A(0),
    B     => B(0),
    cin   => cin,
    s     => s(0),
    cout  => c0
  );

  fa1: fa
  port map (
    A     => A(1)    ,
    B     => B(1)    ,
    cin   => c0     ,
    s     => s(1)    ,
    cout  => c1
  );

  fa2: fa
  port map (
    A     => A(2)    ,
    B     => B(2)    ,
    cin   => c1     ,
    s     => s(2)    ,
    cout  => c2
  );


  fa3: fa
  port map (
    A     => A(3)    ,
    B     => B(3)    ,
    cin   => c2     ,
    s     => s(3)    ,
    cout  => cout
  );

end struct;

playground/src/adder/RCA4/RCA4_tb.vhd
-----------------------------------
-- 4 Bit Ripple Carry Adder
-----------------------------------


library IEEE;
use IEEE.std_logic_1164.all;
use IEEE.numeric_std.all;

-- entity
entity RCA4_tb is
end RCA4_tb;

architecture data_flow of RCA4_tb is

  component RCA4
    port (
      A,B     : in  std_logic_vector(3 downto 0);
      cin     : in  std_logic;
      s       : out std_logic_vector(3 downto 0);
      cout    : out std_logic
    );
  end component;

  signal A,B    : std_logic_vector(3 downto 0);
  signal cin    : std_logic;

begin

  dut: RCA4
  port map (
    A     => a    ,
    B     => b    ,
    cin   => cin  ,
    s     => open ,
    cout  => open
  );


  stim_proc: process
  begin
    A   <= "0000";
    B   <= "0000";
    cin <= '0';

    wait for 100 ns;
    ----------------------------------------------- 
    -- Since this is a 4-Bit Ripple Carry Adder
    -- We have 2pow(4):= 16 test vecotors
    -- It's not good to create the test vectors using loop but its better than manually define them
    ----------------------------------------------- 
    -- generate 16 test vectors considering cin:=0;
    
    for i in 0 to 15 loop
      A   <= std_logic_vector(TO_SIGNED(i,4));
      for j in 0 to 15 loop
        B   <= std_logic_vector(TO_SIGNED(j,4));
        wait for 100 ns;
      end loop;
    end loop;

    cin <= '1';
    -- generate 16 test vectors considering cin:=1;
    for i in 0 to 15 loop
      a   <= std_logic_vector(TO_SIGNED(i,4));
      for j in 0 to 15 loop
        b   <= std_logic_vector(TO_SIGNED(j,4));
        wait for 100 ns;
      end loop;
    end loop;

    wait;
  end process stim_proc;

end data_flow;

playground/src/adder/RCA4/rca.vcd
$date
  Sat Apr 13 23:57:11 2019
$end
$version
  GHDL v0
$end
$timescale
  1 fs
$end
$scope module standard $end
$upscope $end
$scope module std_logic_1164 $end
$upscope $end
$scope module numeric_std $end
$upscope $end
$scope module rca4_tb $end
$var reg 4 ! a[3:0] $end
$var reg 4 " b[3:0] $end
$var reg 1 # cin $end
$scope module dut $end
$var reg 4 $ a[3:0] $end
$var reg 4 % b[3:0] $end
$var reg 1 & cin $end
$var reg 4 ' s[3:0] $end
$var reg 1 ( cout $end
$var reg 1 ) c0 $end
$var reg 1 * c1 $end
$var reg 1 + c2 $end
$scope module fa0 $end
$var reg 1 , a $end
$var reg 1 - b $end
$var reg 1 . cin $end
$var reg 1 / s $end
$var reg 1 0 cout $end
$upscope $end
$scope module fa1 $end
$var reg 1 1 a $end
$var reg 1 2 b $end
$var reg 1 3 cin $end
$var reg 1 4 s $end
$var reg 1 5 cout $end
$upscope $end
$scope module fa2 $end
$var reg 1 6 a $end
$var reg 1 7 b $end
$var reg 1 8 cin $end
$var reg 1 9 s $end
$var reg 1 : cout $end
$upscope $end
$scope module fa3 $end
$var reg 1 ; a $end
$var reg 1 < b $end
$var reg 1 = cin $end
$var reg 1 > s $end
$var reg 1 ? cout $end
$upscope $end
$upscope $end
$upscope $end
$enddefinitions $end
#0
b0000 !
b0000 "
0#
b0000 $
b0000 %
0&
b0000 '
0(
0)
0*
0+
0,
0-
0.
0/
00
01
02
03
04
05
06
07
08
09
0:
0;
0<
0=
0>
0?
#100000000
#200000000
b0001 "
b0001 %
b0001 '
1-
1/
#300000000
b0010 "
b0010 %
b0010 '
0-
0/
12
14
#400000000
b0011 "
b0011 %
b0011 '
1-
1/
#500000000
b0100 "
b0100 %
b0100 '
0-
0/
02
04
17
19
#600000000
b0101 "
b0101 %
b0101 '
1-
1/
#700000000
b0110 "
b0110 %
b0110 '
0-
0/
12
14
#800000000
b0111 "
b0111 %
b0111 '
1-
1/
#900000000
b1000 "
b1000 %
b1000 '
0-
0/
02
04
07
09
1<
1>
#1000000000
b1001 "
b1001 %
b1001 '
1-
1/
#1100000000
b1010 "
b1010 %
b1010 '
0-
0/
12
14
#1200000000
b1011 "
b1011 %
b1011 '
1-
1/
#1300000000
b1100 "
b1100 %
b1100 '
0-
0/
02
04
17
19
#1400000000
b1101 "
b1101 %
b1101 '
1-
1/
#1500000000
b1110 "
b1110 %
b1110 '
0-
0/
12
14
#1600000000
b1111 "
b1111 %
b1111 '
1-
1/
#1700000000
b0001 !
b0000 "
b0001 $
b0000 %
b0001 '
1,
0-
02
04
07
09
0<
0>
#1800000000
b0001 "
b0001 %
b0010 '
1)
1-
0/
10
13
14
#1900000000
b0010 "
b0010 %
b0011 '
0)
0*
0-
1/
00
12
03
14
05
08
09
#2000000000
b0011 "
b0011 %
b0100 '
1)
1*
1-
0/
10
13
04
15
18
19
#2100000000
b0100 "
b0100 %
b0101 '
0)
0*
0+
0-
1/
00
02
03
04
05
17
08
19
0:
0=
0>
#2200000000
b0101 "
b0101 %
b0110 '
1)
1-
0/
10
13
14
#2300000000
b0110 "
b0110 %
b0111 '
0)
0*
0+
0-
1/
00
12
03
14
05
08
19
0:
0=
0>
#2400000000
b0111 "
b0111 %
b1000 '
1)
1*
1+
1-
0/
10
13
04
15
18
09
1:
1=
1>
#2500000000
b1000 "
b1000 %
b1001 '
0(
0)
0*
0+
0-
1/
00
02
03
04
05
07
08
09
0:
1<
0=
1>
0?
#2600000000
b1001 "
b1001 %
b1010 '
1)
1-
0/
10
13
14
#2700000000
b1010 "
b1010 %
b1011 '
0)
0*
0-
1/
00
12
03
14
05
08
09
#2800000000
b1011 "
b1011 %
b1100 '
1)
1*
1-
0/
10
13
04
15
18
19
#2900000000
b1100 "
b1100 %
b1101 '
0(
0)
0*
0+
0-
1/
00
02
03
04
05
17
08
19
0:
0=
1>
0?
#3000000000
b1101 "
b1101 %
b1110 '
1)
1-
0/
10
13
14
#3100000000
b1110 "
b1110 %
b1111 '
0(
0)
0*
0+
0-
1/
00
12
03
14
05
08
19
0:
0=
1>
0?
#3200000000
b1111 "
b1111 %
b0000 '
1(
1)
1*
1+
1-
0/
10
13
04
15
18
09
1:
1=
0>
1?
#3300000000
b0010 !
b0000 "
b0010 $
b0000 %
b0010 '
0(
0)
0*
0+
0,
0-
00
11
02
03
14
05
07
08
09
0:
0<
0=
0>
0?
#3400000000
b0001 "
b0001 %
b0011 '
1-
1/
#3500000000
b0010 "
b0010 %
b0100 '
1*
0-
0/
12
04
15
18
19
#3600000000
b0011 "
b0011 %
b0101 '
1-
1/
#3700000000
b0100 "
b0100 %
b0110 '
0*
0+
0-
0/
02
14
05
17
08
19
0:
0=
0>
#3800000000
b0101 "
b0101 %
b0111 '
1-
1/
#3900000000
b0110 "
b0110 %
b1000 '
1*
1+
0-
0/
12
04
15
18
09
1:
1=
1>
#4000000000
b0111 "
b0111 %
b1001 '
1-
1/
#4100000000
b1000 "
b1000 %
b1010 '
0(
0*
0+
0-
0/
02
14
05
07
08
09
0:
1<
0=
1>
0?
#4200000000
b1001 "
b1001 %
b1011 '
1-
1/
#4300000000
b1010 "
b1010 %
b1100 '
1*
0-
0/
12
04
15
18
19
#4400000000
b1011 "
b1011 %
b1101 '
1-
1/
#4500000000
b1100 "
b1100 %
b1110 '
0(
0*
0+
0-
0/
02
14
05
17
08
19
0:
0=
1>
0?
#4600000000
b1101 "
b1101 %
b1111 '
1-
1/
#4700000000
b1110 "
b1110 %
b0000 '
1(
1*
1+
0-
0/
12
04
15
18
09
1:
1=
0>
1?
#4800000000
b1111 "
b1111 %
b0001 '
1-
1/
#4900000000
b0011 !
b0000 "
b0011 $
b0000 %
b0011 '
0(
0*
0+
1,
0-
02
14
05
07
08
09
0:
0<
0=
0>
0?
#5000000000
b0001 "
b0001 %
b0100 '
1)
1*
1-
0/
10
13
04
15
18
19
#5100000000
b0010 "
b0010 %
b0101 '
0)
0-
1/
00
12
03
04
#5200000000
b0011 "
b0011 %
b0110 '
1)
1-
0/
10
13
14
#5300000000
b0100 "
b0100 %
b0111 '
0)
0*
0+
0-
1/
00
02
03
14
05
17
08
19
0:
0=
0>
#5400000000
b0101 "
b0101 %
b1000 '
1)
1*
1+
1-
0/
10
13
04
15
18
09
1:
1=
1>
#5500000000
b0110 "
b0110 %
b1001 '
0)
0-
1/
00
12
03
04
#5600000000
b0111 "
b0111 %
b1010 '
1)
1-
0/
10
13
14
#5700000000
b1000 "
b1000 %
b1011 '
0(
0)
0*
0+
0-
1/
00
02
03
14
05
07
08
09
0:
1<
0=
1>
0?
#5800000000
b1001 "
b1001 %
b1100 '
1)
1*
1-
0/
10
13
04
15
18
19
#5900000000
b1010 "
b1010 %
b1101 '
0)
0-
1/
00
12
03
04
#6000000000
b1011 "
b1011 %
b1110 '
1)
1-
0/
10
13
14
#6100000000
b1100 "
b1100 %
b1111 '
0(
0)
0*
0+
0-
1/
00
02
03
14
05
17
08
19
0:
0=
1>
0?
#6200000000
b1101 "
b1101 %
b0000 '
1(
1)
1*
1+
1-
0/
10
13
04
15
18
09
1:
1=
0>
1?
#6300000000
b1110 "
b1110 %
b0001 '
0)
0-
1/
00
12
03
04
#6400000000
b1111 "
b1111 %
b0010 '
1)
1-
0/
10
13
14
#6500000000
b0100 !
b0000 "
b0100 $
b0000 %
b0100 '
0(
0)
0*
0+
0,
0-
00
01
02
03
04
05
16
07
08
19
0:
0<
0=
0>
0?
#6600000000
b0001 "
b0001 %
b0101 '
1-
1/
#6700000000
b0010 "
b0010 %
b0110 '
0-
0/
12
14
#6800000000
b0011 "
b0011 %
b0111 '
1-
1/
#6900000000
b0100 "
b0100 %
b1000 '
1+
0-
0/
02
04
17
09
1:
1=
1>
#7000000000
b0101 "
b0101 %
b1001 '
1-
1/
#7100000000
b0110 "
b0110 %
b1010 '
0-
0/
12
14
#7200000000
b0111 "
b0111 %
b1011 '
1-
1/
#7300000000
b1000 "
b1000 %
b1100 '
0(
0+
0-
0/
02
04
07
19
0:
1<
0=
1>
0?
#7400000000
b1001 "
b1001 %
b1101 '
1-
1/
#7500000000
b1010 "
b1010 %
b1110 '
0-
0/
12
14
#7600000000
b1011 "
b1011 %
b1111 '
1-
1/
#7700000000
b1100 "
b1100 %
b0000 '
1(
1+
0-
0/
02
04
17
09
1:
1=
0>
1?
#7800000000
b1101 "
b1101 %
b0001 '
1-
1/
#7900000000
b1110 "
b1110 %
b0010 '
0-
0/
12
14
#8000000000
b1111 "
b1111 %
b0011 '
1-
1/
#8100000000
b0101 !
b0000 "
b0101 $
b0000 %
b0101 '
0(
0+
1,
0-
02
04
07
19
0:
0<
0=
0>
0?
#8200000000
b0001 "
b0001 %
b0110 '
1)
1-
0/
10
13
14
#8300000000
b0010 "
b0010 %
b0111 '
0)
0*
0+
0-
1/
00
12
03
14
05
08
19
0:
0=
0>
#8400000000
b0011 "
b0011 %
b1000 '
1)
1*
1+
1-
0/
10
13
04
15
18
09
1:
1=
1>
#8500000000
b0100 "
b0100 %
b1001 '
0)
0*
0-
1/
00
02
03
04
05
17
08
09
#8600000000
b0101 "
b0101 %
b1010 '
1)
1-
0/
10
13
14
#8700000000
b0110 "
b0110 %
b1011 '
0)
0*
0-
1/
00
12
03
14
05
08
09
#8800000000
b0111 "
b0111 %
b1100 '
1)
1*
1-
0/
10
13
04
15
18
19
#8900000000
b1000 "
b1000 %
b1101 '
0(
0)
0*
0+
0-
1/
00
02
03
04
05
07
08
19
0:
1<
0=
1>
0?
#9000000000
b1001 "
b1001 %
b1110 '
1)
1-
0/
10
13
14
#9100000000
b1010 "
b1010 %
b1111 '
0(
0)
0*
0+
0-
1/
00
12
03
14
05
08
19
0:
0=
1>
0?
#9200000000
b1011 "
b1011 %
b0000 '
1(
1)
1*
1+
1-
0/
10
13
04
15
18
09
1:
1=
0>
1?
#9300000000
b1100 "
b1100 %
b0001 '
0)
0*
0-
1/
00
02
03
04
05
17
08
09
#9400000000
b1101 "
b1101 %
b0010 '
1)
1-
0/
10
13
14
#9500000000
b1110 "
b1110 %
b0011 '
0)
0*
0-
1/
00
12
03
14
05
08
09
#9600000000
b1111 "
b1111 %
b0100 '
1)
1*
1-
0/
10
13
04
15
18
19
#9700000000
b0110 !
b0000 "
b0110 $
b0000 %
b0110 '
0(
0)
0*
0+
0,
0-
00
11
02
03
14
05
07
08
19
0:
0<
0=
0>
0?
#9800000000
b0001 "
b0001 %
b0111 '
1-
1/
#9900000000
b0010 "
b0010 %
b1000 '
1*
1+
0-
0/
12
04
15
18
09
1:
1=
1>
#10000000000
b0011 "
b0011 %
b1001 '
1-
1/
#10100000000
b0100 "
b0100 %
b1010 '
0*
0-
0/
02
14
05
17
08
09
#10200000000
b0101 "
b0101 %
b1011 '
1-
1/
#10300000000
b0110 "
b0110 %
b1100 '
1*
0-
0/
12
04
15
18
19
#10400000000
b0111 "
b0111 %
b1101 '
1-
1/
#10500000000
b1000 "
b1000 %
b1110 '
0(
0*
0+
0-
0/
02
14
05
07
08
19
0:
1<
0=
1>
0?
#10600000000
b1001 "
b1001 %
b1111 '
1-
1/
#10700000000
b1010 "
b1010 %
b0000 '
1(
1*
1+
0-
0/
12
04
15
18
09
1:
1=
0>
1?
#10800000000
b1011 "
b1011 %
b0001 '
1-
1/
#10900000000
b1100 "
b1100 %
b0010 '
0*
0-
0/
02
14
05
17
08
09
#11000000000
b1101 "
b1101 %
b0011 '
1-
1/
#11100000000
b1110 "
b1110 %
b0100 '
1*
0-
0/
12
04
15
18
19
#11200000000
b1111 "
b1111 %
b0101 '
1-
1/
#11300000000
b0111 !
b0000 "
b0111 $
b0000 %
b0111 '
0(
0*
0+
1,
0-
02
14
05
07
08
19
0:
0<
0=
0>
0?
#11400000000
b0001 "
b0001 %
b1000 '
1)
1*
1+
1-
0/
10
13
04
15
18
09
1:
1=
1>
#11500000000
b0010 "
b0010 %
b1001 '
0)
0-
1/
00
12
03
04
#11600000000
b0011 "
b0011 %
b1010 '
1)
1-
0/
10
13
14
#11700000000
b0100 "
b0100 %
b1011 '
0)
0*
0-
1/
00
02
03
14
05
17
08
09
#11800000000
b0101 "
b0101 %
b1100 '
1)
1*
1-
0/
10
13
04
15
18
19
#11900000000
b0110 "
b0110 %
b1101 '
0)
0-
1/
00
12
03
04
#12000000000
b0111 "
b0111 %
b1110 '
1)
1-
0/
10
13
14
#12100000000
b1000 "
b1000 %
b1111 '
0(
0)
0*
0+
0-
1/
00
02
03
14
05
07
08
19
0:
1<
0=
1>
0?
#12200000000
b1001 "
b1001 %
b0000 '
1(
1)
1*
1+
1-
0/
10
13
04
15
18
09
1:
1=
0>
1?
#12300000000
b1010 "
b1010 %
b0001 '
0)
0-
1/
00
12
03
04
#12400000000
b1011 "
b1011 %
b0010 '
1)
1-
0/
10
13
14
#12500000000
b1100 "
b1100 %
b0011 '
0)
0*
0-
1/
00
02
03
14
05
17
08
09
#12600000000
b1101 "
b1101 %
b0100 '
1)
1*
1-
0/
10
13
04
15
18
19
#12700000000
b1110 "
b1110 %
b0101 '
0)
0-
1/
00
12
03
04
#12800000000
b1111 "
b1111 %
b0110 '
1)
1-
0/
10
13
14
#12900000000
b1000 !
b0000 "
b1000 $
b0000 %
b1000 '
0(
0)
0*
0+
0,
0-
00
01
02
03
04
05
06
07
08
09
0:
1;
0<
0=
1>
0?
#13000000000
b0001 "
b0001 %
b1001 '
1-
1/
#13100000000
b0010 "
b0010 %
b1010 '
0-
0/
12
14
#13200000000
b0011 "
b0011 %
b1011 '
1-
1/
#13300000000
b0100 "
b0100 %
b1100 '
0-
0/
02
04
17
19
#13400000000
b0101 "
b0101 %
b1101 '
1-
1/
#13500000000
b0110 "
b0110 %
b1110 '
0-
0/
12
14
#13600000000
b0111 "
b0111 %
b1111 '
1-
1/
#13700000000
b1000 "
b1000 %
b0000 '
1(
0-
0/
02
04
07
09
1<
0>
1?
#13800000000
b1001 "
b1001 %
b0001 '
1-
1/
#13900000000
b1010 "
b1010 %
b0010 '
0-
0/
12
14
#14000000000
b1011 "
b1011 %
b0011 '
1-
1/
#14100000000
b1100 "
b1100 %
b0100 '
0-
0/
02
04
17
19
#14200000000
b1101 "
b1101 %
b0101 '
1-
1/
#14300000000
b1110 "
b1110 %
b0110 '
0-
0/
12
14
#14400000000
b1111 "
b1111 %
b0111 '
1-
1/
#14500000000
b1001 !
b0000 "
b1001 $
b0000 %
b1001 '
0(
1,
0-
02
04
07
09
0<
1>
0?
#14600000000
b0001 "
b0001 %
b1010 '
1)
1-
0/
10
13
14
#14700000000
b0010 "
b0010 %
b1011 '
0)
0*
0-
1/
00
12
03
14
05
08
09
#14800000000
b0011 "
b0011 %
b1100 '
1)
1*
1-
0/
10
13
04
15
18
19
#14900000000
b0100 "
b0100 %
b1101 '
0(
0)
0*
0+
0-
1/
00
02
03
04
05
17
08
19
0:
0=
1>
0?
#15000000000
b0101 "
b0101 %
b1110 '
1)
1-
0/
10
13
14
#15100000000
b0110 "
b0110 %
b1111 '
0(
0)
0*
0+
0-
1/
00
12
03
14
05
08
19
0:
0=
1>
0?
#15200000000
b0111 "
b0111 %
b0000 '
1(
1)
1*
1+
1-
0/
10
13
04
15
18
09
1:
1=
0>
1?
#15300000000
b1000 "
b1000 %
b0001 '
0)
0*
0+
0-
1/
00
02
03
04
05
07
08
09
0:
1<
0=
0>
#15400000000
b1001 "
b1001 %
b0010 '
1)
1-
0/
10
13
14
#15500000000
b1010 "
b1010 %
b0011 '
0)
0*
0-
1/
00
12
03
14
05
08
09
#15600000000
b1011 "
b1011 %
b0100 '
1)
1*
1-
0/
10
13
04
15
18
19
#15700000000
b1100 "
b1100 %
b0101 '
0)
0*
0+
0-
1/
00
02
03
04
05
17
08
19
0:
0=
0>
#15800000000
b1101 "
b1101 %
b0110 '
1)
1-
0/
10
13
14
#15900000000
b1110 "
b1110 %
b0111 '
0)
0*
0+
0-
1/
00
12
03
14
05
08
19
0:
0=
0>
#16000000000
b1111 "
b1111 %
b1000 '
1)
1*
1+
1-
0/
10
13
04
15
18
09
1:
1=
1>
#16100000000
b1010 !
b0000 "
b1010 $
b0000 %
b1010 '
0(
0)
0*
0+
0,
0-
00
11
02
03
14
05
07
08
09
0:
0<
0=
1>
0?
#16200000000
b0001 "
b0001 %
b1011 '
1-
1/
#16300000000
b0010 "
b0010 %
b1100 '
1*
0-
0/
12
04
15
18
19
#16400000000
b0011 "
b0011 %
b1101 '
1-
1/
#16500000000
b0100 "
b0100 %
b1110 '
0(
0*
0+
0-
0/
02
14
05
17
08
19
0:
0=
1>
0?
#16600000000
b0101 "
b0101 %
b1111 '
1-
1/
#16700000000
b0110 "
b0110 %
b0000 '
1(
1*
1+
0-
0/
12
04
15
18
09
1:
1=
0>
1?
#16800000000
b0111 "
b0111 %
b0001 '
1-
1/
#16900000000
b1000 "
b1000 %
b0010 '
0*
0+
0-
0/
02
14
05
07
08
09
0:
1<
0=
0>
#17000000000
b1001 "
b1001 %
b0011 '
1-
1/
#17100000000
b1010 "
b1010 %
b0100 '
1*
0-
0/
12
04
15
18
19
#17200000000
b1011 "
b1011 %
b0101 '
1-
1/
#17300000000
b1100 "
b1100 %
b0110 '
0*
0+
0-
0/
02
14
05
17
08
19
0:
0=
0>
#17400000000
b1101 "
b1101 %
b0111 '
1-
1/
#17500000000
b1110 "
b1110 %
b1000 '
1*
1+
0-
0/
12
04
15
18
09
1:
1=
1>
#17600000000
b1111 "
b1111 %
b1001 '
1-
1/
#17700000000
b1011 !
b0000 "
b1011 $
b0000 %
b1011 '
0(
0*
0+
1,
0-
02
14
05
07
08
09
0:
0<
0=
1>
0?
#17800000000
b0001 "
b0001 %
b1100 '
1)
1*
1-
0/
10
13
04
15
18
19
#17900000000
b0010 "
b0010 %
b1101 '
0)
0-
1/
00
12
03
04
#18000000000
b0011 "
b0011 %
b1110 '
1)
1-
0/
10
13
14
#18100000000
b0100 "
b0100 %
b1111 '
0(
0)
0*
0+
0-
1/
00
02
03
14
05
17
08
19
0:
0=
1>
0?
#18200000000
b0101 "
b0101 %
b0000 '
1(
1)
1*
1+
1-
0/
10
13
04
15
18
09
1:
1=
0>
1?
#18300000000
b0110 "
b0110 %
b0001 '
0)
0-
1/
00
12
03
04
#18400000000
b0111 "
b0111 %
b0010 '
1)
1-
0/
10
13
14
#18500000000
b1000 "
b1000 %
b0011 '
0)
0*
0+
0-
1/
00
02
03
14
05
07
08
09
0:
1<
0=
0>
#18600000000
b1001 "
b1001 %
b0100 '
1)
1*
1-
0/
10
13
04
15
18
19
#18700000000
b1010 "
b1010 %
b0101 '
0)
0-
1/
00
12
03
04
#18800000000
b1011 "
b1011 %
b0110 '
1)
1-
0/
10
13
14
#18900000000
b1100 "
b1100 %
b0111 '
0)
0*
0+
0-
1/
00
02
03
14
05
17
08
19
0:
0=
0>
#19000000000
b1101 "
b1101 %
b1000 '
1)
1*
1+
1-
0/
10
13
04
15
18
09
1:
1=
1>
#19100000000
b1110 "
b1110 %
b1001 '
0)
0-
1/
00
12
03
04
#19200000000
b1111 "
b1111 %
b1010 '
1)
1-
0/
10
13
14
#19300000000
b1100 !
b0000 "
b1100 $
b0000 %
b1100 '
0(
0)
0*
0+
0,
0-
00
01
02
03
04
05
16
07
08
19
0:
0<
0=
1>
0?
#19400000000
b0001 "
b0001 %
b1101 '
1-
1/
#19500000000
b0010 "
b0010 %
b1110 '
0-
0/
12
14
#19600000000
b0011 "
b0011 %
b1111 '
1-
1/
#19700000000
b0100 "
b0100 %
b0000 '
1(
1+
0-
0/
02
04
17
09
1:
1=
0>
1?
#19800000000
b0101 "
b0101 %
b0001 '
1-
1/
#19900000000
b0110 "
b0110 %
b0010 '
0-
0/
12
14
#20000000000
b0111 "
b0111 %
b0011 '
1-
1/
#20100000000
b1000 "
b1000 %
b0100 '
0+
0-
0/
02
04
07
19
0:
1<
0=
0>
#20200000000
b1001 "
b1001 %
b0101 '
1-
1/
#20300000000
b1010 "
b1010 %
b0110 '
0-
0/
12
14
#20400000000
b1011 "
b1011 %
b0111 '
1-
1/
#20500000000
b1100 "
b1100 %
b1000 '
1+
0-
0/
02
04
17
09
1:
1=
1>
#20600000000
b1101 "
b1101 %
b1001 '
1-
1/
#20700000000
b1110 "
b1110 %
b1010 '
0-
0/
12
14
#20800000000
b1111 "
b1111 %
b1011 '
1-
1/
#20900000000
b1101 !
b0000 "
b1101 $
b0000 %
b1101 '
0(
0+
1,
0-
02
04
07
19
0:
0<
0=
1>
0?
#21000000000
b0001 "
b0001 %
b1110 '
1)
1-
0/
10
13
14
#21100000000
b0010 "
b0010 %
b1111 '
0(
0)
0*
0+
0-
1/
00
12
03
14
05
08
19
0:
0=
1>
0?
#21200000000
b0011 "
b0011 %
b0000 '
1(
1)
1*
1+
1-
0/
10
13
04
15
18
09
1:
1=
0>
1?
#21300000000
b0100 "
b0100 %
b0001 '
0)
0*
0-
1/
00
02
03
04
05
17
08
09
#21400000000
b0101 "
b0101 %
b0010 '
1)
1-
0/
10
13
14
#21500000000
b0110 "
b0110 %
b0011 '
0)
0*
0-
1/
00
12
03
14
05
08
09
#21600000000
b0111 "
b0111 %
b0100 '
1)
1*
1-
0/
10
13
04
15
18
19
#21700000000
b1000 "
b1000 %
b0101 '
0)
0*
0+
0-
1/
00
02
03
04
05
07
08
19
0:
1<
0=
0>
#21800000000
b1001 "
b1001 %
b0110 '
1)
1-
0/
10
13
14
#21900000000
b1010 "
b1010 %
b0111 '
0)
0*
0+
0-
1/
00
12
03
14
05
08
19
0:
0=
0>
#22000000000
b1011 "
b1011 %
b1000 '
1)
1*
1+
1-
0/
10
13
04
15
18
09
1:
1=
1>
#22100000000
b1100 "
b1100 %
b1001 '
0)
0*
0-
1/
00
02
03
04
05
17
08
09
#22200000000
b1101 "
b1101 %
b1010 '
1)
1-
0/
10
13
14
#22300000000
b1110 "
b1110 %
b1011 '
0)
0*
0-
1/
00
12
03
14
05
08
09
#22400000000
b1111 "
b1111 %
b1100 '
1)
1*
1-
0/
10
13
04
15
18
19
#22500000000
b1110 !
b0000 "
b1110 $
b0000 %
b1110 '
0(
0)
0*
0+
0,
0-
00
11
02
03
14
05
07
08
19
0:
0<
0=
1>
0?
#22600000000
b0001 "
b0001 %
b1111 '
1-
1/
#22700000000
b0010 "
b0010 %
b0000 '
1(
1*
1+
0-
0/
12
04
15
18
09
1:
1=
0>
1?
#22800000000
b0011 "
b0011 %
b0001 '
1-
1/
#22900000000
b0100 "
b0100 %
b0010 '
0*
0-
0/
02
14
05
17
08
09
#23000000000
b0101 "
b0101 %
b0011 '
1-
1/
#23100000000
b0110 "
b0110 %
b0100 '
1*
0-
0/
12
04
15
18
19
#23200000000
b0111 "
b0111 %
b0101 '
1-
1/
#23300000000
b1000 "
b1000 %
b0110 '
0*
0+
0-
0/
02
14
05
07
08
19
0:
1<
0=
0>
#23400000000
b1001 "
b1001 %
b0111 '
1-
1/
#23500000000
b1010 "
b1010 %
b1000 '
1*
1+
0-
0/
12
04
15
18
09
1:
1=
1>
#23600000000
b1011 "
b1011 %
b1001 '
1-
1/
#23700000000
b1100 "
b1100 %
b1010 '
0*
0-
0/
02
14
05
17
08
09
#23800000000
b1101 "
b1101 %
b1011 '
1-
1/
#23900000000
b1110 "
b1110 %
b1100 '
1*
0-
0/
12
04
15
18
19
#24000000000
b1111 "
b1111 %
b1101 '
1-
1/
#24100000000
b1111 !
b0000 "
b1111 $
b0000 %
b1111 '
0(
0*
0+
1,
0-
02
14
05
07
08
19
0:
0<
0=
1>
0?
#24200000000
b0001 "
b0001 %
b0000 '
1(
1)
1*
1+
1-
0/
10
13
04
15
18
09
1:
1=
0>
1?
#24300000000
b0010 "
b0010 %
b0001 '
0)
0-
1/
00
12
03
04
#24400000000
b0011 "
b0011 %
b0010 '
1)
1-
0/
10
13
14
#24500000000
b0100 "
b0100 %
b0011 '
0)
0*
0-
1/
00
02
03
14
05
17
08
09
#24600000000
b0101 "
b0101 %
b0100 '
1)
1*
1-
0/
10
13
04
15
18
19
#24700000000
b0110 "
b0110 %
b0101 '
0)
0-
1/
00
12
03
04
#24800000000
b0111 "
b0111 %
b0110 '
1)
1-
0/
10
13
14
#24900000000
b1000 "
b1000 %
b0111 '
0)
0*
0+
0-
1/
00
02
03
14
05
07
08
19
0:
1<
0=
0>
#25000000000
b1001 "
b1001 %
b1000 '
1)
1*
1+
1-
0/
10
13
04
15
18
09
1:
1=
1>
#25100000000
b1010 "
b1010 %
b1001 '
0)
0-
1/
00
12
03
04
#25200000000
b1011 "
b1011 %
b1010 '
1)
1-
0/
10
13
14
#25300000000
b1100 "
b1100 %
b1011 '
0)
0*
0-
1/
00
02
03
14
05
17
08
09
#25400000000
b1101 "
b1101 %
b1100 '
1)
1*
1-
0/
10
13
04
15
18
19
#25500000000
b1110 "
b1110 %
b1101 '
0)
0-
1/
00
12
03
04
#25600000000
b1111 "
b1111 %
b1110 '
1)
1-
0/
10
13
14
#25700000000
b0000 !
b0000 "
1#
b0000 $
b0000 %
1&
b0001 '
0(
0)
0*
0+
0,
0-
1.
1/
00
01
02
03
04
05
06
07
08
09
0:
0;
0<
0=
0>
0?
#25800000000
b0001 "
b0001 %
b0010 '
1)
1-
0/
10
13
14
#25900000000
b0010 "
b0010 %
b0011 '
0)
0*
0-
1/
00
12
03
14
05
08
09
#26000000000
b0011 "
b0011 %
b0100 '
1)
1*
1-
0/
10
13
04
15
18
19
#26100000000
b0100 "
b0100 %
b0101 '
0)
0*
0+
0-
1/
00
02
03
04
05
17
08
19
0:
0=
0>
#26200000000
b0101 "
b0101 %
b0110 '
1)
1-
0/
10
13
14
#26300000000
b0110 "
b0110 %
b0111 '
0)
0*
0+
0-
1/
00
12
03
14
05
08
19
0:
0=
0>
#26400000000
b0111 "
b0111 %
b1000 '
1)
1*
1+
1-
0/
10
13
04
15
18
09
1:
1=
1>
#26500000000
b1000 "
b1000 %
b1001 '
0(
0)
0*
0+
0-
1/
00
02
03
04
05
07
08
09
0:
1<
0=
1>
0?
#26600000000
b1001 "
b1001 %
b1010 '
1)
1-
0/
10
13
14
#26700000000
b1010 "
b1010 %
b1011 '
0)
0*
0-
1/
00
12
03
14
05
08
09
#26800000000
b1011 "
b1011 %
b1100 '
1)
1*
1-
0/
10
13
04
15
18
19
#26900000000
b1100 "
b1100 %
b1101 '
0(
0)
0*
0+
0-
1/
00
02
03
04
05
17
08
19
0:
0=
1>
0?
