playground/src/adder/RCA_N/FA.vhd
library ieee;
use ieee.std_logic_1164.ALL;
---------------------------------------------------------------------------------------------
-- FullAdder Implementation
-- Implementation of Full Adder using structural design pattern (gate_Level)
-- Testbench is Included under the name FA_tb
-- For Modularity this module is reused to create a Ripple Carry Adder RCA4
--          This is achieved by redefining the FA component in RCA4.vhd file
---------------------------------------------------------------------------------------------
entity FA is
  port (
    A, B, cin : in std_logic;
    s, cout   : out std_logic);
end FA;


architecture structure of FA is
begin
    s <= A XOR B XOR cin;
    cout <= (A AND B) OR (cin AND A) OR (cin AND B);

end structure;

playground/src/adder/FA/FA_tb.vhd
library ieee;
use ieee.std_logic_1164.ALL;

--TODO
-- To change data into std_ulogic

---------------------------------------------------------------------------------------------
-- FullAdder TESTBENCH Implementation
---------------------------------------------------------------------------------------------
entity FA_tb is
end FA_tb;

---------------------------------------------------------------------------------------------
-- Architecture for 1 bit Full Adder
---------------------------------------------------------------------------------------------
architecture data_flow of FA_tb is

  -- Define a Component of DUT(Design Under Test);
  component FA
  port(
    A, B, cin   : in std_logic;
    s, cout     : out std_logic);
  end component;


  -- Inputs
  signal A    : std_logic := '0';
  signal B    : std_logic := '0';
  signal cin  : std_logic := '0';

  -- Output
   signal s    : std_logic;
   signal cout : std_logic;


begin
  --Instantiate (DUT)
  dut: FA port map (
    A     => A,
    B     => B,
    cin   =>cin,
    s     =>s,
    cout  =>cout);

    -- Stimulus process
  stim_proc: process
  begin
    -- hold reset state
    wait for 100 ns;
    -- insert stimulus; Applying Drivers for all Test Vectors 2power(3) test cases
    A <= '1';
    B <= '0';
    cin <= '0';
    wait for 100 ns;

    A <= '0';
    B <= '1';
    cin <= '0';
    wait for 100 ns;

    A <= '1';
    B <= '1';
    cin <= '0';
    wait for 100 ns;

    A <= '0';
    B <= '0';
    cin <= '1';
    wait for 100 ns;

    A <= '1';
    B <= '0';
    cin <= '1';
    wait for 100 ns;

    A <= '0';
    B <= '1';
    cin <= '1';
    wait for 100 ns;

    A <= '1';
    B <= '1';
    cin <= '1';
    wait for 100 ns;
    wait;
  end process stim_proc;

end data_flow;

playground/src/adder/FA/fa.vcd
$date
  Sun Apr 21 20:57:36 2019
$end
$version
  GHDL v0
$end
$timescale
  1 fs
$end
$scope module standard $end
$upscope $end
$scope module std_logic_1164 $end
$upscope $end
$scope module fa_tb $end
$var reg 1 ! a $end
$var reg 1 " b $end
$var reg 1 # cin $end
$var reg 1 $ s $end
$var reg 1 % cout $end
$scope module dut $end
$var reg 1 & a $end
$var reg 1 ' b $end
$var reg 1 ( cin $end
$var reg 1 ) s $end
$var reg 1 * cout $end
$upscope $end
$upscope $end
$enddefinitions $end
#0
0!
0"
0#
0$
0%
0&
0'
0(
0)
0*
#100000000
1!
1$
1&
1)
#200000000
0!
1"
0&
1'
#300000000
1!
0$
1%
1&
0)
1*
#400000000
0!
0"
1#
1$
0%
0&
0'
1(
1)
0*
#500000000
1!
0$
1%
1&
0)
1*
#600000000
0!
1"
0&
1'
#700000000
1!
1$
1&
1)
