wireless_comm/qam_mapper.vhd
---------------------------------------------------------
-- QAM MAPPER
---------------------------------------------------------
-- we want to have one single change of bits from one symbol to the other;
-- thus, using fixed point number[gray code] representation {00, 01, 11, 10} to represent {1+1j, -1+1j, -1-1j, 1-1j} 
-- Constellation	|	Symbols
-- {00}			|	{+1+J}
-- {01}			|	{-1+J}
-- {10}			|	{+1-J}
-- {11}			|	{-1-J}
---------------------------------------------------------
library IEEE;
use IEEE.STD_LOGIC_1164.ALL;
use IEEE.NUMERIC_STD.ALL;

ENTITY qam_mapper is
	port (
		data_in		: in std_logic_vector (1 downto 0);
		I_symbols	: out std_logic_vector (1 downto 0);
		Q_symbols	: out std_logic_vector (1 downto 0)
	);
	
END qam_mapper;

ARCHITECTURE Behaviourl of qam_mapper is
	-- define array for both I and Q parts (4 constellation points)
	-- Constellation Size; to be generic however the modulation order
	constant const_size : integer := 4;
	-- Constellation Type
	type constellation is array (0 to const_size-1) of signed (1 downto 0);
	-- I array
	-- to_signed: Converts an INTEGER to a SIGNED vector of the specified SIZE.
	constant I_data	: constellation := (
		to_signed(1,2),
		to_signed(-1,2),
		to_signed(1,2),
		to_signed(-1,2)
		);
	-- Q array
	constant Q_data	: constellation := (
		to_signed(1,2),
		to_signed(1,2),
		to_signed(-1,2),
		to_signed(-1,2)
		); 
	signal bits_in_unsigned : unsigned (1 downto 0);
begin
	-- to get from std_logic_vector to integer: > we go to unsigned then to integer 
	-- s.t input data is needed to index the constellation array
	bits_in_unsigned 	<= unsigned(data_in);
	-- Mapping of Input Data/Bits into QAM symbols
	I_symbols 		<= std_logic_vector(I_data(to_integer(bits_in_unsigned)));
	Q_symbols 		<= std_logic_vector(Q_data(to_integer(bits_in_unsigned)));

end Behaviourl;

wireless_comm/mapping_tb.vhd
library IEEE;
use IEEE.STD_LOGIC_1164.ALL;
use IEEE.NUMERIC_STD.ALL;

ENTITY mapping_tb is
END mapping_tb;

ARCHITECTURE Behavioral of mapping_tb is

	--Define the clock as 100 MHz
	constant clk_period : time :=10 ns;
	--Define a signal called clk
	signal clk : std_logic;
	signal rst : std_logic;
	signal twobitcount : unsigned(1 downto 0);
	signal tx_bits : std_logic_vector(1 downto 0); 


component qam_mapper is
        port (
                data_in         : in std_logic_vector (1 downto 0);
                I_symbols       : out std_logic_vector (1 downto 0);
                Q_symbols       : out std_logic_vector (1 downto 0)
        );
end component;


begin
-----------------------------------------------------------------------
-- PROCESSES: Clock and Reset Generation
-----------------------------------------------------------------------
	-- This process is (while(1)) repeasts forever 
	clk_gen : process 
	begin
		clk <= '0';
		wait for clk_period/2;
		clk <= '1';
		wait for clk_period/2;
	end process;
	
	reset_gen : process
	begin
		rst <= '1'; -- reset is active at the begining of the simulation
		wait for 2*clk_period;
		rst <= '0';
		wait; -- uncoditional wait
	end process;
-----------------------------------------------------------------------
-----------------------------------------------------------------------
-- PROCESSE: TWO bit COUNTER
-- synch counter to be assinged to data_in
-----------------------------------------------------------------------
	-- clk and rst are passed the sensitivity list
	count_proc : process(clk, rst)
	begin
		if (rst = '1') then
			twobitcount <= (others => '0'); -- means all bits in the counter will be set to 0
		elsif (rising_edge(clk)) then
			twobitcount <= twobitcount + 1; -- increment the counter for each rising edge of the clk
		end if;
	end process;
-----------------------------------------------------------------------
	tx_bits <= std_logic_vector(twobitcount);
		
-----------------------------------------------------------------------
-- PROCESSE: QAM Transmitter bit COUNTER
-----------------------------------------------------------------------
	
	-- create a label qam_mapper_i to qam_mapper
	-- qam_mapper the developed module, which is in the work library (default lib)
	qam_mapper_i :  qam_mapper
		-- mapping to signals 
		port map (
			data_in		=> tx_bits,
			I_symbols	=> open,
			Q_symbols	=> open
		);

end Behavioral;

wireless_comm/mapper.vcd
$date
  Tue Apr 30 09:32:28 2019
$end
$version
  GHDL v0
$end
$timescale
  1 fs
$end
$scope module standard $end
$upscope $end
$scope module std_logic_1164 $end
$upscope $end
$scope module numeric_std $end
$upscope $end
$scope module mapping_tb $end
$var reg 1 ! clk $end
$var reg 1 " rst $end
$var reg 2 # twobitcount[1:0] $end
$var reg 2 $ tx_bits[1:0] $end
$scope module qam_mapper_i $end
$var reg 2 % data_in[1:0] $end
$var reg 2 & i_symbols[1:0] $end
$var reg 2 ' q_symbols[1:0] $end
$var reg 2 ( bits_in_unsigned[1:0] $end
$upscope $end
$upscope $end
$enddefinitions $end
#0
0!
1"
b00 #
b00 $
b00 %
b01 &
b01 '
b00 (
#5000000
1!
#10000000
0!
#15000000
1!
#20000000
0!
0"
#25000000
1!
b01 #
b01 $
b01 %
b11 &
b01 (
#30000000
0!
#35000000
1!
b10 #
b10 $
b10 %
b01 &
b11 '
b10 (
#40000000
0!
#45000000
1!
b11 #
b11 $
b11 %
b11 &
b11 (
#50000000
0!
#55000000
1!
b00 #
b00 $
b00 %
b01 &
b01 '
b00 (
#60000000
0!
#65000000
1!
b01 #
b01 $
b01 %
b11 &
b01 (
#70000000
0!
#75000000
1!
b10 #
b10 $
b10 %
b01 &
b11 '
b10 (
#80000000
0!
#85000000
1!
b11 #
b11 $
b11 %
b11 &
b11 (
#90000000
0!
#95000000
1!
b00 #
b00 $
b00 %
b01 &
b01 '
b00 (
#100000000
0!
#105000000
1!
b01 #
b01 $
b01 %
b11 &
b01 (
#110000000
0!
#115000000
1!
b10 #
b10 $
b10 %
b01 &
b11 '
b10 (
#120000000
0!
#125000000
1!
b11 #
b11 $
b11 %
b11 &
b11 (
#130000000
0!
#135000000
1!
b00 #
b00 $
b00 %
b01 &
b01 '
b00 (
#140000000
0!
#145000000
1!
b01 #
b01 $
b01 %
b11 &
b01 (
#150000000
0!
#155000000
1!
b10 #
b10 $
b10 %
b01 &
b11 '
b10 (
#160000000
0!
#165000000
1!
b11 #
b11 $
b11 %
b11 &
b11 (
#170000000
0!
#175000000
1!
b00 #
b00 $
b00 %
b01 &
b01 '
b00 (
#180000000
0!
#185000000
1!
b01 #
b01 $
b01 %
b11 &
b01 (
#190000000
0!
#195000000
1!
b10 #
b10 $
b10 %
b01 &
b11 '
b10 (
#200000000
0!
#205000000
1!
b11 #
b11 $
b11 %
b11 &
b11 (
#210000000
0!
#215000000
1!
b00 #
b00 $
b00 %
b01 &
b01 '
b00 (
#220000000
0!
#225000000
1!
b01 #
b01 $
b01 %
b11 &
b01 (
#230000000
0!
#235000000
1!
b10 #
b10 $
b10 %
b01 &
b11 '
b10 (
#240000000
0!
#245000000
1!
b11 #
b11 $
b11 %
b11 &
b11 (
#250000000
0!
#255000000
1!
b00 #
b00 $
b00 %
b01 &
b01 '
b00 (
#260000000
0!
#265000000
1!
b01 #
b01 $
b01 %
b11 &
b01 (
#270000000
0!
#275000000
1!
b10 #
b10 $
b10 %
b01 &
b11 '
b10 (
#280000000
0!
#285000000
1!
b11 #
b11 $
b11 %
b11 &
b11 (
#290000000
0!
#295000000
1!
b00 #
b00 $
b00 %
b01 &
b01 '
b00 (
#300000000
0!
#305000000
1!
b01 #
b01 $
b01 %
b11 &
b01 (
#310000000
0!
#315000000
1!
b10 #
b10 $
b10 %
b01 &
b11 '
b10 (
#320000000
0!
#325000000
1!
b11 #
b11 $
b11 %
b11 &
b11 (
#330000000
0!
#335000000
1!
b00 #
b00 $
b00 %
b01 &
b01 '
b00 (
#340000000
0!
#345000000
1!
b01 #
b01 $
b01 %
b11 &
b01 (
#350000000
0!
#355000000
1!
b10 #
b10 $
b10 %
b01 &
b11 '
b10 (
#360000000
0!
#365000000
1!
b11 #
b11 $
b11 %
b11 &
b11 (
#370000000
0!
#375000000
1!
b00 #
b00 $
b00 %
b01 &
b01 '
b00 (
#380000000
0!
#385000000
1!
b01 #
b01 $
b01 %
b11 &
b01 (
#390000000
0!
#395000000
1!
b10 #
b10 $
b10 %
b01 &
b11 '
b10 (
#400000000
0!
#405000000
1!
b11 #
b11 $
b11 %
b11 &
b11 (
#410000000
0!
#415000000
1!
b00 #
b00 $
b00 %
b01 &
b01 '
b00 (
#420000000
0!
#425000000
1!
b01 #
b01 $
b01 %
b11 &
b01 (
#430000000
0!
#435000000
1!
b10 #
b10 $
b10 %
b01 &
b11 '
b10 (
#440000000
0!
#445000000
1!
b11 #
b11 $
b11 %
b11 &
b11 (
#450000000
0!
#455000000
1!
b00 #
b00 $
b00 %
b01 &
b01 '
b00 (
#460000000
0!
#465000000
1!
b01 #
b01 $
b01 %
b11 &
b01 (
#470000000
0!
#475000000
1!
b10 #
b10 $
b10 %
b01 &
b11 '
b10 (
#480000000
0!
#485000000
1!
b11 #
b11 $
b11 %
b11 &
b11 (
#490000000
0!
#495000000
1!
b00 #
b00 $
b00 %
b01 &
b01 '
b00 (
#500000000
0!
#505000000
1!
b01 #
b01 $
b01 %
b11 &
b01 (
#510000000
0!
#515000000
1!
b10 #
b10 $
b10 %
b01 &
b11 '
b10 (
#520000000
0!
#525000000
1!
b11 #
b11 $
b11 %
b11 &
b11 (
#530000000
0!
#535000000
1!
b00 #
b00 $
b00 %
b01 &
b01 '
b00 (
#540000000
0!
#545000000
1!
b01 #
b01 $
b01 %
b11 &
b01 (
#550000000
0!
#555000000
1!
b10 #
b10 $
b10 %
b01 &
b11 '
b10 (
#560000000
0!
#565000000
1!
b11 #
b11 $
b11 %
b11 &
b11 (
#570000000
0!
#575000000
1!
b00 #
b00 $
b00 %
b01 &
b01 '
b00 (
#580000000
0!
#585000000
1!
b01 #
b01 $
b01 %
b11 &
b01 (
#590000000
0!
#595000000
1!
b10 #
b10 $
b10 %
b01 &
b11 '
b10 (
#600000000
0!
#605000000
1!
b11 #
b11 $
b11 %
b11 &
b11 (
#610000000
0!
#615000000
1!
b00 #
b00 $
b00 %
b01 &
b01 '
b00 (
#620000000
0!
#625000000
1!
b01 #
b01 $
b01 %
b11 &
b01 (
#630000000
0!
#635000000
1!
b10 #
b10 $
b10 %
b01 &
b11 '
b10 (
#640000000
0!
#645000000
1!
b11 #
b11 $
b11 %
b11 &
b11 (
#650000000
0!
#655000000
1!
b00 #
b00 $
b00 %
b01 &
b01 '
b00 (
#660000000
0!
#665000000
1!
b01 #
b01 $
b01 %
b11 &
b01 (
#670000000
0!
#675000000
1!
b10 #
b10 $
b10 %
b01 &
b11 '
b10 (
#680000000
0!
#685000000
1!
b11 #
b11 $
b11 %
b11 &
b11 (
#690000000
0!
#695000000
1!
b00 #
b00 $
b00 %
b01 &
b01 '
b00 (
#700000000
0!
#705000000
1!
b01 #
b01 $
b01 %
b11 &
b01 (
#710000000
0!
#715000000
1!
b10 #
b10 $
b10 %
b01 &
b11 '
b10 (
#720000000
0!
#725000000
1!
b11 #
b11 $
b11 %
b11 &
b11 (
#730000000
0!
#735000000
1!
b00 #
b00 $
b00 %
b01 &
b01 '
b00 (
#740000000
0!
#745000000
1!
b01 #
b01 $
b01 %
b11 &
b01 (
#750000000
0!
#755000000
1!
b10 #
b10 $
b10 %
b01 &
b11 '
b10 (
#760000000
0!
#765000000
1!
b11 #
b11 $
b11 %
b11 &
b11 (
#770000000
0!
#775000000
1!
b00 #
b00 $
b00 %
b01 &
b01 '
b00 (
#780000000
0!
#785000000
1!
b01 #
b01 $
b01 %
b11 &
b01 (
#790000000
0!
#795000000
1!
b10 #
b10 $
b10 %
b01 &
b11 '
b10 (
#800000000
0!
#805000000
1!
b11 #
b11 $
b11 %
b11 &
b11 (
#810000000
0!
#815000000
1!
b00 #
b00 $
b00 %
b01 &
b01 '
b00 (
#820000000
0!
#825000000
1!
b01 #
b01 $
b01 %
b11 &
b01 (
#830000000
0!
#835000000
1!
b10 #
b10 $
b10 %
b01 &
b11 '
b10 (
#840000000
0!
#845000000
1!
b11 #
b11 $
b11 %
b11 &
b11 (
#850000000
0!
#855000000
1!
b00 #
b00 $
b00 %
b01 &
b01 '
b00 (
#860000000
0!
#865000000
1!
b01 #
b01 $
b01 %
b11 &
b01 (
#870000000
0!
#875000000
1!
b10 #
b10 $
b10 %
b01 &
b11 '
b10 (
#880000000
0!
#885000000
1!
b11 #
b11 $
b11 %
b11 &
b11 (
#890000000
0!
#895000000
1!
b00 #
b00 $
b00 %
b01 &
b01 '
b00 (
#900000000
0!
#905000000
1!
b01 #
b01 $
b01 %
b11 &
b01 (
#910000000
0!
#915000000
1!
b10 #
b10 $
b10 %
b01 &
b11 '
b10 (
#920000000
0!
#925000000
1!
b11 #
b11 $
b11 %
b11 &
b11 (
#930000000
0!
#935000000
1!
b00 #
b00 $
b00 %
b01 &
b01 '
b00 (
#940000000
0!
#945000000
1!
b01 #
b01 $
b01 %
b11 &
b01 (
#950000000
0!
#955000000
1!
b10 #
b10 $
b10 %
b01 &
b11 '
b10 (
#960000000
0!
#965000000
1!
b11 #
b11 $
b11 %
b11 &
b11 (
#970000000
0!
#975000000
1!
b00 #
b00 $
b00 %
b01 &
b01 '
b00 (
#980000000
0!
#985000000
1!
b01 #
b01 $
b01 %
b11 &
b01 (
#990000000
0!
#995000000
1!
b10 #
b10 $
b10 %
b01 &
b11 '
b10 (
#1000000000
0!
#1005000000
1!
b11 #
b11 $
b11 %
b11 &
b11 (
#1010000000
0!
#1015000000
1!
b00 #
b00 $
b00 %
b01 &
b01 '
b00 (
#1020000000
0!
#1025000000
1!
b01 #
b01 $
b01 %
b11 &
b01 (
#1030000000
0!
#1035000000
1!
b10 #
b10 $
b10 %
b01 &
b11 '
b10 (
#1040000000
0!
#1045000000
1!
b11 #
b11 $
b11 %
b11 &
b11 (
#1050000000
0!
#1055000000
1!
b00 #
b00 $
b00 %
b01 &
b01 '
b00 (
#1060000000
0!
#1065000000
1!
b01 #
b01 $
b01 %
b11 &
b01 (
#1070000000
0!
#1075000000
1!
b10 #
b10 $
b10 %
b01 &
b11 '
b10 (
#1080000000
0!
#1085000000
1!
b11 #
b11 $
b11 %
b11 &
b11 (
#1090000000
0!
#1095000000
1!
b00 #
b00 $
b00 %
b01 &
b01 '
b00 (
#1100000000
0!
#1105000000
1!
b01 #
b01 $
b01 %
b11 &
b01 (
#1110000000
0!
#1115000000
1!
b10 #
b10 $
b10 %
b01 &
b11 '
b10 (
#1120000000
0!
#1125000000
1!
b11 #
b11 $
b11 %
b11 &
b11 (
#1130000000
0!
#1135000000
1!
b00 #
b00 $
b00 %
b01 &
b01 '
b00 (
#1140000000
0!
#1145000000
1!
b01 #
b01 $
b01 %
b11 &
b01 (
#1150000000
0!
#1155000000
1!
b10 #
b10 $
b10 %
b01 &
b11 '
b10 (
#1160000000
0!
#1165000000
1!
b11 #
b11 $
b11 %
b11 &
b11 (
#1170000000
0!
#1175000000
1!
b00 #
b00 $
b00 %
b01 &
b01 '
b00 (
#1180000000
0!
#1185000000
1!
b01 #
b01 $
b01 %
b11 &
b01 (
#1190000000
0!
#1195000000
1!
b10 #
b10 $
b10 %
b01 &
b11 '
b10 (
#1200000000
0!
#1205000000
1!
b11 #
b11 $
b11 %
b11 &
b11 (
#1210000000
0!
#1215000000
1!
b00 #
b00 $
b00 %
b01 &
b01 '
b00 (
#1220000000
0!
#1225000000
1!
b01 #
b01 $
b01 %
b11 &
b01 (
#1230000000
0!
#1235000000
1!
b10 #
b10 $
b10 %
b01 &
b11 '
b10 (
#1240000000
0!
#1245000000
1!
b11 #
b11 $
b11 %
b11 &
b11 (
#1250000000
0!
#1255000000
1!
b00 #
b00 $
b00 %
b01 &
b01 '
b00 (
#1260000000
0!
#1265000000
1!
b01 #
b01 $
b01 %
b11 &
b01 (
#1270000000
0!
#1275000000
1!
b10 #
b10 $
b10 %
b01 &
b11 '
b10 (
#1280000000
0!
#1285000000
1!
b11 #
b11 $
b11 %
b11 &
b11 (
#1290000000
0!
#1295000000
1!
b00 #
b00 $
b00 %
b01 &
b01 '
b00 (
#1300000000
0!
#1305000000
1!
b01 #
b01 $
b01 %
b11 &
b01 (
#1310000000
0!
#1315000000
1!
b10 #
b10 $
b10 %
b01 &
b11 '
b10 (
#1320000000
0!
#1325000000
1!
b11 #
b11 $
b11 %
b11 &
b11 (
#1330000000
0!
#1335000000
1!
b00 #
b00 $
b00 %
b01 &
b01 '
b00 (
#1340000000
0!
#1345000000
1!
b01 #
b01 $
b01 %
b11 &
b01 (
#1350000000
0!
#1355000000
1!
b10 #
b10 $
b10 %
b01 &
b11 '
b10 (
#1360000000
0!
#1365000000
1!
b11 #
b11 $
b11 %
b11 &
b11 (
#1370000000
0!
#1375000000
1!
b00 #
b00 $
b00 %
b01 &
b01 '
b00 (
#1380000000
0!
#1385000000
1!
b01 #
b01 $
b01 %
b11 &
b01 (
#1390000000
0!
#1395000000
1!
b10 #
b10 $
b10 %
b01 &
b11 '
b10 (
#1400000000
0!
#1405000000
1!
b11 #
b11 $
b11 %
b11 &
b11 (
#1410000000
0!
#1415000000
1!
b00 #
b00 $
b00 %
b01 &
b01 '
b00 (
#1420000000
0!
#1425000000
1!
b01 #
b01 $
b01 %
b11 &
b01 (
#1430000000
0!
#1435000000
1!
b10 #
b10 $
b10 %
b01 &
b11 '
b10 (
#1440000000
0!
#1445000000
1!
b11 #
b11 $
b11 %
b11 &
b11 (
#1450000000
0!
#1455000000
1!
b00 #
b00 $
b00 %
b01 &
b01 '
b00 (
#1460000000
0!
#1465000000
1!
b01 #
b01 $
b01 %
b11 &
b01 (
#1470000000
0!
#1475000000
1!
b10 #
b10 $
b10 %
b01 &
b11 '
b10 (
#1480000000
0!
#1485000000
1!
b11 #
b11 $
b11 %
b11 &
b11 (
#1490000000
0!
#1495000000
1!
b00 #
b00 $
b00 %
b01 &
b01 '
b00 (
#1500000000
0!
#1505000000
1!
b01 #
b01 $
b01 %
b11 &
b01 (
#1510000000
0!
#1515000000
1!
b10 #
b10 $
b10 %
b01 &
b11 '
b10 (
#1520000000
0!
#1525000000
1!
b11 #
b11 $
b11 %
b11 &
b11 (
#1530000000
0!
#1535000000
1!
b00 #
b00 $
b00 %
b01 &
b01 '
b00 (
#1540000000
0!
#1545000000
1!
b01 #
b01 $
b01 %
b11 &
b01 (
#1550000000
0!
#1555000000
1!
b10 #
b10 $
b10 %
b01 &
b11 '
b10 (
#1560000000
0!
#1565000000
1!
b11 #
b11 $
b11 %
b11 &
b11 (
#1570000000
0!
#1575000000
1!
b00 #
b00 $
b00 %
b01 &
b01 '
b00 (
#1580000000
0!
#1585000000
1!
b01 #
b01 $
b01 %
b11 &
b01 (
#1590000000
0!
#1595000000
1!
b10 #
b10 $
b10 %
b01 &
b11 '
b10 (
#1600000000
0!
#1605000000
1!
b11 #
b11 $
b11 %
b11 &
b11 (
#1610000000
0!
#1615000000
1!
b00 #
b00 $
b00 %
b01 &
b01 '
b00 (
#1620000000
0!
#1625000000
1!
b01 #
b01 $
b01 %
b11 &
b01 (
#1630000000
0!
#1635000000
1!
b10 #
b10 $
b10 %
b01 &
b11 '
b10 (
#1640000000
0!
#1645000000
1!
b11 #
b11 $
b11 %
b11 &
b11 (
#1650000000
0!
#1655000000
1!
b00 #
b00 $
b00 %
b01 &
b01 '
b00 (
#1660000000
0!
#1665000000
1!
b01 #
b01 $
b01 %
b11 &
b01 (
#1670000000
0!
#1675000000
1!
b10 #
b10 $
b10 %
b01 &
b11 '
b10 (
#1680000000
0!
#1685000000
1!
b11 #
b11 $
b11 %
b11 &
b11 (
#1690000000
0!
#1695000000
1!
b00 #
b00 $
b00 %
b01 &
b01 '
b00 (
#1700000000
0!
#1705000000
1!
b01 #
b01 $
b01 %
b11 &
b01 (
#1710000000
0!
#1715000000
1!
b10 #
b10 $
b10 %
b01 &
b11 '
b10 (
#1720000000
0!
#1725000000
1!
b11 #
b11 $
b11 %
b11 &
b11 (
#1730000000
0!
#1735000000
1!
b00 #
b00 $
b00 %
b01 &
b01 '
b00 (
#1740000000
0!
#1745000000
1!
b01 #
b01 $
b01 %
b11 &
b01 (
#1750000000
0!
#1755000000
1!
b10 #
b10 $
b10 %
b01 &
b11 '
b10 (
#1760000000
0!
#1765000000
1!
b11 #
b11 $
b11 %
b11 &
b11 (
#1770000000
0!
#1775000000
1!
b00 #
b00 $
b00 %
b01 &
b01 '
b00 (
#1780000000
0!
#1785000000
1!
b01 #
b01 $
b01 %
b11 &
b01 (
#1790000000
0!
#1795000000
1!
b10 #
b10 $
b10 %
b01 &
b11 '
b10 (
#1800000000
0!
#1805000000
1!
b11 #
b11 $
b11 %
b11 &
b11 (
#1810000000
0!
#1815000000
1!
b00 #
b00 $
b00 %
b01 &
b01 '
b00 (
#1820000000
0!
#1825000000
1!
b01 #
b01 $
b01 %
b11 &
b01 (
#1830000000
0!
#1835000000
1!
b10 #
b10 $
b10 %
b01 &
b11 '
b10 (
#1840000000
0!
#1845000000
1!
b11 #
b11 $
b11 %
b11 &
b11 (
#1850000000
0!
#1855000000
1!
b00 #
b00 $
b00 %
b01 &
b01 '
b00 (
#1860000000
0!
#1865000000
1!
b01 #
b01 $
b01 %
b11 &
b01 (
#1870000000
0!
#1875000000
1!
b10 #
b10 $
b10 %
b01 &
b11 '
b10 (
#1880000000
0!
#1885000000
1!
b11 #
b11 $
b11 %
b11 &
b11 (
#1890000000
0!
#1895000000
1!
b00 #
b00 $
b00 %
b01 &
b01 '
b00 (
#1900000000
0!
#1905000000
1!
b01 #
b01 $
b01 %
b11 &
b01 (
#1910000000
0!
#1915000000
1!
b10 #
b10 $
b10 %
b01 &
b11 '
b10 (
#1920000000
0!
#1925000000
1!
b11 #
b11 $
b11 %
b11 &
b11 (
#1930000000
0!
#1935000000
1!
b00 #
b00 $
b00 %
b01 &
b01 '
b00 (
#1940000000
0!
#1945000000
1!
b01 #
b01 $
b01 %
b11 &
b01 (
#1950000000
0!
#1955000000
1!
b10 #
b10 $
b10 %
b01 &
b11 '
b10 (
#1960000000
0!
#1965000000
1!
b11 #
b11 $
b11 %
b11 &
b11 (
#1970000000
0!
#1975000000
1!
b00 #
b00 $
b00 %
b01 &
b01 '
b00 (
#1980000000
0!
#1985000000
1!
b01 #
b01 $
b01 %
b11 &
b01 (
#1990000000
0!
#1995000000
1!
b10 #
b10 $
b10 %
b01 &
b11 '
b10 (
#2000000000
0!
#2005000000
1!
b11 #
b11 $
b11 %
b11 &
b11 (
#2010000000
0!
#2015000000
1!
b00 #
b00 $
b00 %
b01 &
b01 '
b00 (
#2020000000
0!
#2025000000
1!
b01 #
b01 $
b01 %
b11 &
b01 (
#2030000000
0!
#2035000000
1!
b10 #
b10 $
b10 %
b01 &
b11 '
b10 (
#2040000000
0!
#2045000000
1!
b11 #
b11 $
b11 %
b11 &
b11 (
#2050000000
0!
#2055000000
1!
b00 #
b00 $
b00 %
b01 &
b01 '
b00 (
#2060000000
0!
#2065000000
1!
b01 #
b01 $
b01 %
b11 &
b01 (
#2070000000
0!
#2075000000
1!
b10 #
b10 $
b10 %
b01 &
b11 '
b10 (
#2080000000
0!
#2085000000
1!
b11 #
b11 $
b11 %
b11 &
b11 (
#2090000000
0!
#2095000000
1!
b00 #
b00 $
b00 %
b01 &
b01 '
b00 (
#2100000000
0!
#2105000000
1!
b01 #
b01 $
b01 %
b11 &
b01 (
#2110000000
0!
#2115000000
1!
b10 #
b10 $
b10 %
b01 &
b11 '
b10 (
#2120000000
0!
#2125000000
1!
b11 #
b11 $
b11 %
b11 &
b11 (
#2130000000
0!
#2135000000
1!
b00 #
b00 $
b00 %
b01 &
b01 '
b00 (
#2140000000
0!
#2145000000
1!
b01 #
b01 $
b01 %
b11 &
b01 (
#2150000000
0!
#2155000000
1!
b10 #
b10 $
b10 %
b01 &
b11 '
b10 (
#2160000000
0!
#2165000000
1!
b11 #
b11 $
b11 %
b11 &
b11 (
#2170000000
0!
#2175000000
1!
b00 #
b00 $
b00 %
b01 &
b01 '
b00 (
#2180000000
0!
#2185000000
1!
b01 #
b01 $
b01 %
b11 &
b01 (
#2190000000
0!
#2195000000
1!
b10 #
b10 $
b10 %
b01 &
b11 '
b10 (
#2200000000
0!
#2205000000
1!
b11 #
b11 $
b11 %
b11 &
b11 (
#2210000000
0!
#2215000000
1!
b00 #
b00 $
b00 %
b01 &
b01 '
b00 (
#2220000000
0!
#2225000000
1!
b01 #
b01 $
b01 %
b11 &
b01 (
#2230000000
0!
#2235000000
1!
b10 #
b10 $
b10 %
b01 &
b11 '
b10 (
#2240000000
0!
#2245000000
1!
b11 #
b11 $
b11 %
b11 &
b11 (
#2250000000
0!
#2255000000
1!
b00 #
b00 $
b00 %
b01 &
b01 '
b00 (
#2260000000
0!
#2265000000
1!
b01 #
b01 $
b01 %
b11 &
b01 (
#2270000000
0!
#2275000000
1!
b10 #
b10 $
b10 %
b01 &
b11 '
b10 (
#2280000000
0!
#2285000000
1!
b11 #
b11 $
b11 %
b11 &
b11 (
#2290000000
0!
#2295000000
1!
b00 #
b00 $
b00 %
b01 &
b01 '
b00 (
#2300000000
0!
#2305000000
1!
b01 #
b01 $
b01 %
b11 &
b01 (
#2310000000
0!
#2315000000
1!
b10 #
b10 $
b10 %
b01 &
b11 '
b10 (
#2320000000
0!
#2325000000
1!
b11 #
b11 $
b11 %
b11 &
b11 (
#2330000000
0!
#2335000000
1!
b00 #
b00 $
b00 %
b01 &
b01 '
b00 (
#2340000000
0!
#2345000000
1!
b01 #
b01 $
b01 %
b11 &
b01 (
#2350000000
0!
#2355000000
1!
b10 #
b10 $
b10 %
b01 &
b11 '
b10 (
#2360000000
0!
#2365000000
1!
b11 #
b11 $
b11 %
b11 &
b11 (
#2370000000
0!
#2375000000
1!
b00 #
b00 $
b00 %
b01 &
b01 '
b00 (
#2380000000
0!
#2385000000
1!
b01 #
b01 $
b01 %
b11 &
b01 (
#2390000000
0!
#2395000000
1!
b10 #
b10 $
b10 %
b01 &
b11 '
b10 (
#2400000000
0!
#2405000000
1!
b11 #
b11 $
b11 %
b11 &
b11 (
#2410000000
0!
#2415000000
1!
b00 #
b00 $
b00 %
b01 &
b01 '
b00 (
#2420000000
0!
#2425000000
1!
b01 #
b01 $
b01 %
b11 &
b01 (
#2430000000
0!
#2435000000
1!
b10 #
b10 $
b10 %
b01 &
b11 '
b10 (
#2440000000
0!
#2445000000
1!
b11 #
b11 $
b11 %
b11 &
b11 (
#2450000000
0!
#2455000000
1!
b00 #
b00 $
b00 %
b01 &
b01 '
b00 (
#2460000000
0!
#2465000000
1!
b01 #
b01 $
b01 %
b11 &
b01 (
#2470000000
0!
#2475000000
1!
b10 #
b10 $
b10 %
b01 &
b11 '
b10 (
#2480000000
0!
#2485000000
1!
b11 #
b11 $
b11 %
b11 &
b11 (
#2490000000
0!
#2495000000
1!
b00 #
b00 $
b00 %
b01 &
b01 '
b00 (
#2500000000
0!
#2505000000
1!
b01 #
b01 $
b01 %
b11 &
b01 (
#2510000000
0!
#2515000000
1!
b10 #
b10 $
b10 %
b01 &
b11 '
b10 (
#2520000000
0!
#2525000000
1!
b11 #
b11 $
b11 %
b11 &
b11 (
#2530000000
0!
#2535000000
1!
b00 #
b00 $
b00 %
b01 &
b01 '
b00 (
#2540000000
0!
#2545000000
1!
b01 #
b01 $
b01 %
b11 &
b01 (
#2550000000
0!
#2555000000
1!
b10 #
b10 $
b10 %
b01 &
b11 '
b10 (
#2560000000
0!
#2565000000
1!
b11 #
b11 $
b11 %
b11 &
b11 (
#2570000000
0!
#2575000000
1!
b00 #
b00 $
b00 %
b01 &
b01 '
b00 (
#2580000000
0!
#2585000000
1!
b01 #
b01 $
b01 %
b11 &
b01 (
#2590000000
0!
#2595000000
1!
b10 #
b10 $
b10 %
b01 &
b11 '
b10 (
#2600000000
0!
#2605000000
1!
b11 #
b11 $
b11 %
b11 &
b11 (
#2610000000
0!
#2615000000
1!
b00 #
b00 $
b00 %
b01 &
b01 '
b00 (
#2620000000
0!
#2625000000
1!
b01 #
b01 $
b01 %
b11 &
b01 (
#2630000000
0!
#2635000000
1!
b10 #
b10 $
b10 %
b01 &
b11 '
b10 (
#2640000000
0!
#2645000000
1!
b11 #
b11 $
b11 %
b11 &
b11 (
#2650000000
0!
#2655000000
1!
b00 #
b00 $
b00 %
b01 &
b01 '
b00 (
#2660000000
0!
#2665000000
1!
b01 #
b01 $
b01 %
b11 &
b01 (
#2670000000
0!
#2675000000
1!
b10 #
b10 $
b10 %
b01 &
b11 '
b10 (
#2680000000
0!
#2685000000
1!
b11 #
b11 $
b11 %
b11 &
b11 (
#2690000000
0!
#2695000000
1!
b00 #
b00 $
b00 %
b01 &
b01 '
b00 (
#2700000000
0!
#2705000000
1!
b01 #
b01 $
b01 %
b11 &
b01 (
#2710000000
0!
#2715000000
1!
b10 #
b10 $
b10 %
b01 &
b11 '
b10 (
#2720000000
0!
#2725000000
1!
b11 #
b11 $
b11 %
b11 &
b11 (
#2730000000
0!
#2735000000
1!
b00 #
b00 $
b00 %
b01 &
b01 '
b00 (
#2740000000
0!
#2745000000
1!
b01 #
b01 $
b01 %
b11 &
b01 (
#2750000000
0!
#2755000000
1!
b10 #
b10 $
b10 %
b01 &
b11 '
b10 (
#2760000000
0!
#2765000000
1!
b11 #
b11 $
b11 %
b11 &
b11 (
#2770000000
0!
#2775000000
1!
b00 #
b00 $
b00 %
b01 &
b01 '
b00 (
#2780000000
0!
#2785000000
1!
b01 #
b01 $
b01 %
b11 &
b01 (
#2790000000
0!
#2795000000
1!
b10 #
b10 $
b10 %
b01 &
b11 '
b10 (
#2800000000
0!
#2805000000
1!
b11 #
b11 $
b11 %
b11 &
b11 (
#2810000000
0!
#2815000000
1!
b00 #
b00 $
b00 %
b01 &
b01 '
b00 (
#2820000000
0!
#2825000000
1!
b01 #
b01 $
b01 %
b11 &
b01 (
#2830000000
0!
#2835000000
1!
b10 #
b10 $
b10 %
b01 &
b11 '
b10 (
#2840000000
0!
#2845000000
1!
b11 #
b11 $
b11 %
b11 &
b11 (
#2850000000
0!
#2855000000
1!
b00 #
b00 $
b00 %
b01 &
b01 '
b00 (
